[{"title_clean":"2 Days in Paris ","series":"2 Days in...","date":2007.0,"imdb":6.8},{"title_clean":"2 Days in New York ","series":"2 Days in...","date":2012.0,"imdb":6.0},{"title_clean":"8mm ","series":"8mm","date":1999.0,"imdb":6.5},{"title_clean":"8mm 2 ","series":"8mm","date":2005.0,"imdb":4.5},{"title_clean":"28 Days Later ","series":"28 Days Later","date":2002.0,"imdb":7.6},{"title_clean":"28 Weeks Later ","series":"28 Days Later","date":2007.0,"imdb":7.0},{"title_clean":"30 Days of Night ","series":"30 Days of Night","date":2007.0,"imdb":6.6},{"title_clean":"30 Days of Night: Dark Days ","series":"30 Days of Night","date":2010.0,"imdb":4.4},{"title_clean":"47 Meters Down ","series":"47 Meters Down","date":2017.0,"imdb":5.6},{"title_clean":"47 Meters Down: Uncaged ","series":"47 Meters Down","date":2019.0,"imdb":5.0},{"title_clean":"101 Dalmatians ","series":"101 Dalmatians  (1996 series)","date":1996.0,"imdb":5.7},{"title_clean":"102 Dalmatians ","series":"101 Dalmatians  (1996 series)","date":2000.0,"imdb":4.9},{"title_clean":"300 ","series":"300","date":2007.0,"imdb":6.1},{"title_clean":"300: Rise of an Empire ","series":"300","date":2014.0,"imdb":6.2},{"title_clean":"500 Years Later ","series":"500 Years Later","date":2005.0,"imdb":6.8},{"title_clean":"Motherland ","series":"500 Years Later","date":2010.0,"imdb":8.0},{"title_clean":"666: The Child ","series":"666","date":2006.0,"imdb":2.8},{"title_clean":"666: The Beast ","series":"666","date":2007.0,"imdb":2.7},{"title_clean":"2001 Maniacs ","series":"2001 Maniacs","date":2005.0,"imdb":5.3},{"title_clean":"2001 Maniacs: Field of Screams ","series":"2001 Maniacs","date":2010.0,"imdb":3.2},{"title_clean":"A Dog's Purpose ","series":"A Dog's Purpose","date":2017.0,"imdb":7.2},{"title_clean":"A Dog's Journey ","series":"A Dog's Purpose","date":2019.0,"imdb":7.5},{"title_clean":"A Haunted House ","series":"A Haunted House","date":2013.0,"imdb":5.0},{"title_clean":"A Haunted House 2 ","series":"A Haunted House","date":2014.0,"imdb":4.7},{"title_clean":"Aadu ","series":"Aashiqui","date":2015.0,"imdb":6.8},{"title_clean":"Aadu 2 ","series":"Aashiqui","date":2017.0,"imdb":null},{"title_clean":"Aashiqui 2 ","series":"Aashiqui","date":2013.0,"imdb":7.0},{"title_clean":"Ab Tak Chhappan ","series":"Ab Tak Chhappan","date":2004.0,"imdb":7.8},{"title_clean":"Ab Tak Chhappan 2 ","series":"Ab Tak Chhappan","date":2015.0,"imdb":5.8},{"title_clean":"Abang Long Fadil ","series":"Abang Long Fadil","date":2014.0,"imdb":6.7},{"title_clean":"Abang Long Fadil 2 ","series":"Abang Long Fadil","date":2017.0,"imdb":7.2},{"title_clean":"Agent Cody Banks ","series":"Agent Cody Banks","date":2003.0,"imdb":5.0},{"title_clean":"Agent Cody Banks 2: Destination London ","series":"Agent Cody Banks","date":2004.0,"imdb":4.6},{"title_clean":"Aksar ","series":"Aksar","date":2006.0,"imdb":4.8},{"title_clean":"Aksar 2 ","series":"Aksar","date":2017.0,"imdb":3.6},{"title_clean":"Alice in Wonderland ","series":"Lewis Carroll's Alice (2010 series)","date":2010.0,"imdb":6.4},{"title_clean":"Alice Through the Looking Glass ","series":"Lewis Carroll's Alice (2010 series)","date":2016.0,"imdb":6.2},{"title_clean":"All Hallows' Eve ","series":"All Hallows' Eve","date":2013.0,"imdb":5.0},{"title_clean":"All Hallows' Eve 2 ","series":"All Hallows' Eve","date":2015.0,"imdb":4.8},{"title_clean":"All Stars ","series":"All Stars","date":1997.0,"imdb":7.2},{"title_clean":"All Stars 2: Old Stars ","series":"All Stars","date":2011.0,"imdb":6.2},{"title_clean":"Bruce Almighty ","series":"The Almighty Series","date":2003.0,"imdb":6.8},{"title_clean":"Evan Almighty ","series":"The Almighty Series","date":2007.0,"imdb":5.4},{"title_clean":"Amanush ","series":"Amanush","date":2010.0,"imdb":6.3},{"title_clean":"Amanush 2 ","series":"Amanush","date":2015.0,"imdb":6.4},{"title_clean":"The Amazing Spider-Man ","series":"The Amazing Spider-Man","date":2012.0,"imdb":6.9},{"title_clean":"The Amazing Spider-Man 2 ","series":"The Amazing Spider-Man","date":2014.0,"imdb":6.6},{"title_clean":"American Kickboxer ","series":"American Kickboxer","date":1991.0,"imdb":3.6},{"title_clean":"American Kickboxer 2 ","series":"American Kickboxer","date":1993.0,"imdb":3.6},{"title_clean":"Analyze This ","series":"Analyze This","date":1999.0,"imdb":6.7},{"title_clean":"Analyze That ","series":"Analyze This","date":2002.0,"imdb":5.9},{"title_clean":"Anastasia ","series":"Anastasia","date":1997.0,"imdb":7.2},{"title_clean":"Bartok the Magnificent ","series":"Anastasia","date":1999.0,"imdb":6.1},{"title_clean":"Anatomy ","series":"Anatomy","date":2000.0,"imdb":5.4},{"title_clean":"Anatomy 2 ","series":"Anatomy","date":2003.0,"imdb":5.1},{"title_clean":"Ang probinsyano ","series":"Ang probinsyano","date":1997.0,"imdb":3.4},{"title_clean":"Pagbabalik ng probinsyano ","series":"Ang probinsyano","date":1998.0,"imdb":6.6},{"title_clean":"The Angry Birds Movie ","series":"Angry Birds","date":2016.0,"imdb":6.3},{"title_clean":"The Angry Birds Movie 2 ","series":"Angry Birds","date":2019.0,"imdb":6.4},{"title_clean":"An Inconvenient Truth ","series":"An Inconvenient Truth","date":2006.0,"imdb":7.4},{"title_clean":"An Inconvenient Sequel: Truth to Power ","series":"An Inconvenient Truth","date":2017.0,"imdb":6.4},{"title_clean":"Anni 90 ","series":"Anni 90","date":1992.0,"imdb":4.8},{"title_clean":"Anni 90 - Parte II ","series":"Anni 90","date":1993.0,"imdb":4.1},{"title_clean":"Ano ba iyan? ","series":"Ano ba iyan?","date":1992.0,"imdb":7.8},{"title_clean":"Ano ba 'yan 2 ","series":"Ano ba iyan?","date":1993.0,"imdb":7.6},{"title_clean":"Another Gay Movie ","series":"Another Gay Movie","date":2006.0,"imdb":4.9},{"title_clean":"Another Gay Sequel: Gays Gone Wild! ","series":"Another Gay Movie","date":2008.0,"imdb":4.0},{"title_clean":"Appleseed ","series":"Appleseed","date":2004.0,"imdb":7.0},{"title_clean":"Appleseed Ex Machina ","series":"Appleseed","date":2007.0,"imdb":7.1},{"title_clean":"AR-15: Comando implacable ","series":"AR-15: Comando implacable","date":1992.0,"imdb":5.5},{"title_clean":"AR-15 Comando Implacable II ","series":"AR-15: Comando implacable","date":1997.0,"imdb":4.2},{"title_clean":"Aranmanai ","series":"Aranmanai","date":2014.0,"imdb":5.2},{"title_clean":"Aranmanai 2 ","series":"Aranmanai","date":2016.0,"imdb":4.2},{"title_clean":"A.R.C.H.I.E. ","series":"A.R.C.H.I.E.","date":2016.0,"imdb":5.0},{"title_clean":"A.R.C.H.I.E. 2 ","series":"A.R.C.H.I.E.","date":2018.0,"imdb":4.7},{"title_clean":"Ardaas ","series":"Ardaas","date":2016.0,"imdb":8.4},{"title_clean":"Ardaas Karaan ","series":"Ardaas","date":2019.0,"imdb":9.0},{"title_clean":"Are We There Yet? ","series":"Are We There Yet?","date":2005.0,"imdb":4.7},{"title_clean":"Are We Done Yet? ","series":"Are We There Yet?","date":2007.0,"imdb":4.2},{"title_clean":"Arya ","series":"Arya","date":2004.0,"imdb":7.9},{"title_clean":"Arya 2 ","series":"Arya","date":2009.0,"imdb":7.4},{"title_clean":"A spasso nel tempo ","series":"A spasso nel tempo","date":1996.0,"imdb":4.1},{"title_clean":"A spasso nel tempo: l'avventura continua ","series":"A spasso nel tempo","date":1997.0,"imdb":3.9},{"title_clean":"Atlantis: The Lost Empire ","series":"Disney's Atlantis","date":2001.0,"imdb":6.9},{"title_clean":"Atlantis: Milo's Return ","series":"Disney's Atlantis","date":2003.0,"imdb":5.1},{"title_clean":"Axeman ","series":"Axeman","date":2013.0,"imdb":3.4},{"title_clean":"Axeman 2: Overkill ","series":"Axeman","date":2017.0,"imdb":4.7},{"title_clean":"Ay Lav Yu ","series":"Ay Lav Yu","date":2010.0,"imdb":5.5},{"title_clean":"Ay Lav Yu Tuu ","series":"Ay Lav Yu","date":2017.0,"imdb":3.7},{"title_clean":"Azumi ","series":"Azumi","date":2003.0,"imdb":6.8},{"title_clean":"Azumi 2: Death or Love ","series":"Azumi","date":2005.0,"imdb":6.3},{"title_clean":"Babe ","series":"Babe","date":1995.0,"imdb":6.7},{"title_clean":"Babe: Pig in the City ","series":"Babe","date":1998.0,"imdb":5.7},{"title_clean":"Babysitting ","series":"Babysitting","date":2014.0,"imdb":6.8},{"title_clean":"Babysitting 2 ","series":"Babysitting","date":2015.0,"imdb":6.4},{"title_clean":"Backdraft ","series":"Backdraft","date":1991.0,"imdb":6.7},{"title_clean":"Backdraft 2 ","series":"Backdraft","date":2019.0,"imdb":4.8},{"title_clean":"Bad Lieutenant ","series":"Bad Lieutenant","date":1992.0,"imdb":7.1},{"title_clean":"Bad Lieutenant: Port of Call New Orleans ","series":"Bad Lieutenant","date":2009.0,"imdb":6.6},{"title_clean":"Bad Moms ","series":"Bad Moms","date":2016.0,"imdb":6.2},{"title_clean":"A Bad Moms Christmas ","series":"Bad Moms","date":2017.0,"imdb":5.6},{"title_clean":"Bad Santa ","series":"Bad Santa","date":2003.0,"imdb":7.0},{"title_clean":"Bad Santa 2 ","series":"Bad Santa","date":2016.0,"imdb":5.6},{"title_clean":"Bats ","series":"Bats","date":1999.0,"imdb":3.9},{"title_clean":"Bats: Human Harvest ","series":"Bats","date":2007.0,"imdb":3.2},{"title_clean":"Flags of Our Fathers ","series":"Battle of Iwo Jima","date":2006.0,"imdb":7.1},{"title_clean":"Letters from Iwo Jima ","series":"Battle of Iwo Jima","date":2006.0,"imdb":7.9},{"title_clean":"Battlestar Galactica: Razor ","series":"Battlestar Galactica **","date":2007.0,"imdb":7.6},{"title_clean":"Battlestar Galactica: The Plan ","series":"Battlestar Galactica **","date":2009.0,"imdb":7.1},{"title_clean":"Beer: The Movie ","series":"Beer","date":2006.0,"imdb":5.2},{"title_clean":"Beer: The Movie 2 - Leaving Long Island ","series":"Beer","date":2006.0,"imdb":6.0},{"title_clean":"Belly ","series":"Belly","date":1998.0,"imdb":6.2},{"title_clean":"Belly 2: Millionaire Boyz Club ","series":"Belly","date":2008.0,"imdb":3.4},{"title_clean":"The Benchwarmers ","series":"The Benchwarmers","date":2006.0,"imdb":5.5},{"title_clean":"Benchwarmers 2: Breaking Balls ","series":"The Benchwarmers","date":2019.0,"imdb":4.0},{"title_clean":"The Best Man ","series":"The Best Man","date":1999.0,"imdb":6.8},{"title_clean":"The Best Man Holiday ","series":"The Best Man","date":2013.0,"imdb":6.7},{"title_clean":"Beverly Hills Christmas ","series":"Beverly Hills Christmas","date":2015.0,"imdb":2.9},{"title_clean":"This is Our Christmas ","series":"Beverly Hills Christmas","date":2018.0,"imdb":3.4},{"title_clean":"Bhoot ","series":"Bhoot","date":2003.0,"imdb":6.5},{"title_clean":"Bhoot Returns ","series":"Bhoot","date":2012.0,"imdb":2.5},{"title_clean":"Big Fat Liar ","series":"Big Fat Liar","date":2002.0,"imdb":5.4},{"title_clean":"Bigger Fatter Liar ","series":"Big Fat Liar","date":2017.0,"imdb":4.0},{"title_clean":"Big Money Hustlas ","series":"Big Money Hustlas","date":2000.0,"imdb":6.0},{"title_clean":"Big Money Rustlas ","series":"Big Money Hustlas","date":2010.0,"imdb":4.1},{"title_clean":"The Bikini Carwash Company ","series":"The Bikini Carwash Company","date":1992.0,"imdb":4.7},{"title_clean":"The Bikini Carwash Company II ","series":"The Bikini Carwash Company","date":1993.0,"imdb":3.3},{"title_clean":"Black Mask ","series":"Black Mask","date":1996.0,"imdb":6.1},{"title_clean":"Black Mask 2: City of Masks ","series":"Black Mask","date":2002.0,"imdb":3.5},{"title_clean":"Blind gudinne ","series":"Blind gudinne","date":1997.0,"imdb":5.9},{"title_clean":"Salige er de som t\u00f8rster ","series":"Blind gudinne","date":1997.0,"imdb":5.9},{"title_clean":"Blood Ring ","series":"Blood Ring","date":1991.0,"imdb":4.2},{"title_clean":"Blood Ring 2 ","series":"Blood Ring","date":1995.0,"imdb":5.1},{"title_clean":"Bloody Murder ","series":"Bloody Murder","date":2000.0,"imdb":3.0},{"title_clean":"Bloody Murder 2: Closing Camp ","series":"Bloody Murder","date":2003.0,"imdb":4.4},{"title_clean":"Blue Collar Comedy Tour: The Movie ","series":"Blue Dollar Comedy Tour *","date":2003.0,"imdb":7.1},{"title_clean":"Blue Collar Comedy Tour Rides Again ","series":"Blue Dollar Comedy Tour *","date":2004.0,"imdb":7.1},{"title_clean":"Blue Crush ","series":"Blue Crush","date":2002.0,"imdb":5.6},{"title_clean":"Blue Crush 2 ","series":"Blue Crush","date":2011.0,"imdb":5.4},{"title_clean":"The Bodyguard ","series":"The Bodyguard","date":2004.0,"imdb":5.8},{"title_clean":"The Bodyguard 2 ","series":"The Bodyguard","date":2007.0,"imdb":5.4},{"title_clean":"Bonded by Blood ","series":"Bonded by Blood","date":2010.0,"imdb":5.5},{"title_clean":"Bonded by Blood 2 ","series":"Bonded by Blood","date":2017.0,"imdb":5.9},{"title_clean":"Bones ","series":"Bones","date":2003.0,"imdb":5.8},{"title_clean":"Hush ","series":"Bones","date":2005.0,"imdb":5.0},{"title_clean":"The Boondock Saints ","series":"The Boondock Saints","date":1999.0,"imdb":7.8},{"title_clean":"The Boondock Saints II: All Saints Day ","series":"The Boondock Saints","date":2009.0,"imdb":6.3},{"title_clean":"Born to Race ","series":"Born to Race","date":2011.0,"imdb":6.0},{"title_clean":"Born to Race: Fast Track ","series":"Born to Race","date":2014.0,"imdb":5.3},{"title_clean":"Bounty Hunters ","series":"Bounty Hunters","date":1996.0,"imdb":4.5},{"title_clean":"Hardball ","series":"Bounty Hunters","date":1997.0,"imdb":4.5},{"title_clean":"The Boy ","series":"The Boy","date":2016.0,"imdb":6.0},{"title_clean":"Brahms: The Boy II ","series":"The Boy","date":2020.0,"imdb":4.6},{"title_clean":"Boyz ","series":"Boyz","date":2017.0,"imdb":7.8},{"title_clean":"Boyz 2 ","series":"Boyz","date":2018.0,"imdb":7.1},{"title_clean":"The Bride with White Hair ","series":"The Bride with White Hair","date":1993.0,"imdb":6.9},{"title_clean":"The Bride with White Hair 2 ","series":"The Bride with White Hair","date":1993.0,"imdb":6.1},{"title_clean":"Brother Bear ","series":"Disney's Brother Bear (2003) (A)","date":2003.0,"imdb":6.8},{"title_clean":"Brother Bear 2 ","series":"Disney's Brother Bear (2003) (A)","date":2006.0,"imdb":6.2},{"title_clean":"Buck ai confini del cielo ","series":"Buck","date":1991.0,"imdb":5.1},{"title_clean":"Buck and the Magic Bracelet ","series":"Buck","date":1999.0,"imdb":3.8},{"title_clean":"Buena Vista Social Club ","series":"Buena Vista Social Club","date":1999.0,"imdb":7.7},{"title_clean":"Buena Vista Social Club: Adios ","series":"Buena Vista Social Club","date":2017.0,"imdb":7.0},{"title_clean":"Bulletproof ","series":"Bulletproof","date":1996.0,"imdb":5.8},{"title_clean":"Bulletproof 2 ","series":"Bulletproof","date":2020.0,"imdb":3.5},{"title_clean":"Cabin by the Lake ","series":"Cabin by the Lake","date":2000.0,"imdb":5.7},{"title_clean":"Return to Cabin by the Lake ","series":"Cabin by the Lake","date":2001.0,"imdb":4.3},{"title_clean":"Cabin Fever ","series":"Cabin Fever","date":2002.0,"imdb":5.7},{"title_clean":"Cabin Fever 2: Spring Fever ","series":"Cabin Fever","date":2009.0,"imdb":4.3},{"title_clean":"Call for Love ","series":"Call for Love","date":2007.0,"imdb":5.8},{"title_clean":"Fit Lover ","series":"Call for Love","date":2008.0,"imdb":4.3},{"title_clean":"Camp Rock ","series":"Camp Rock","date":2008.0,"imdb":5.2},{"title_clean":"Camp Rock 2: The Final Jam ","series":"Camp Rock","date":2010.0,"imdb":5.2},{"title_clean":"Carlito's Way ","series":"Carlito's Way","date":1993.0,"imdb":7.9},{"title_clean":"Carlito's Way: Rise to Power ","series":"Carlito's Way","date":2005.0,"imdb":5.0},{"title_clean":"Carry On Jatta ","series":"Carry On Jatta","date":2012.0,"imdb":8.3},{"title_clean":"Carry On Jatta 2 ","series":"Carry On Jatta","date":2018.0,"imdb":7.0},{"title_clean":"Cats & Dogs ","series":"Cats & Dogs","date":2001.0,"imdb":5.1},{"title_clean":"Cats & Dogs: The Revenge of Kitty Galore ","series":"Cats & Dogs","date":2010.0,"imdb":4.3},{"title_clean":"The Cell ","series":"The Cell","date":2000.0,"imdb":6.3},{"title_clean":"The Cell 2 ","series":"The Cell","date":2009.0,"imdb":2.8},{"title_clean":"Chandramukhi ","series":"Chandramukhi","date":2005.0,"imdb":7.0},{"title_clean":"Nagavalli ","series":"Chandramukhi","date":2010.0,"imdb":4.6},{"title_clean":"Chasing the Dragon ","series":"Chasing the Dragon","date":2017.0,"imdb":6.8},{"title_clean":"Chasing the Dragon II: Wild Wild Bunch ","series":"Chasing the Dragon","date":2019.0,"imdb":5.8},{"title_clean":"Cheaper by the Dozen ","series":"Cheaper by the Dozen  (2003 series)","date":2003.0,"imdb":5.9},{"title_clean":"Cheaper by the Dozen 2 ","series":"Cheaper by the Dozen  (2003 series)","date":2005.0,"imdb":5.5},{"title_clean":"Get Shorty ","series":"Chili Palmer","date":1995.0,"imdb":6.9},{"title_clean":"Be Cool ","series":"Chili Palmer","date":2005.0,"imdb":5.6},{"title_clean":"Chirodini Tumi Je Amar ","series":"Chirodini Tumi Je Amar","date":2008.0,"imdb":6.6},{"title_clean":"Chirodini Tumi Je Amar 2 ","series":"Chirodini Tumi Je Amar","date":2014.0,"imdb":7.5},{"title_clean":"Christmas with a Prince ","series":"Christmas with a Prince","date":2018.0,"imdb":5.3},{"title_clean":"Christmas with a Prince: Becoming Royal ","series":"Christmas with a Prince","date":2019.0,"imdb":5.9},{"title_clean":"CIA Code Name: Alexa ","series":"CIA Code Name: Alexa","date":1992.0,"imdb":4.4},{"title_clean":"CIA II: Target Alexa ","series":"CIA Code Name: Alexa","date":1993.0,"imdb":3.8},{"title_clean":"City Slickers ","series":"City Slickers","date":1991.0,"imdb":6.7},{"title_clean":"City Slickers II: The Legend of Curly's Gold ","series":"City Slickers","date":1994.0,"imdb":5.6},{"title_clean":"Clash of the Titans ","series":"Clash of the Titans","date":2010.0,"imdb":5.8},{"title_clean":"Wrath of the Titans ","series":"Clash of the Titans","date":2012.0,"imdb":5.7},{"title_clean":"Cloudy with a Chance of Meatballs ","series":"Cloudy with a Chance of Meatballs","date":2009.0,"imdb":6.9},{"title_clean":"Cloudy with a Chance of Meatballs 2 ","series":"Cloudy with a Chance of Meatballs","date":2013.0,"imdb":6.4},{"title_clean":"The Collector ","series":"The Collector","date":2009.0,"imdb":6.4},{"title_clean":"The Collection ","series":"The Collector","date":2012.0,"imdb":6.1},{"title_clean":"The Condemned ","series":"The Condemned","date":2007.0,"imdb":6.0},{"title_clean":"The Condemned 2 ","series":"The Condemned","date":2015.0,"imdb":4.1},{"title_clean":"Aqu\u00ed llega Condemor, el pecador de la pradera ","series":"Condemor","date":1996.0,"imdb":2.5},{"title_clean":"Br\u00e1cula. Condemor II ","series":"Condemor","date":1997.0,"imdb":3.0},{"title_clean":"Contracted ","series":"Contracted","date":2013.0,"imdb":5.3},{"title_clean":"Contracted: Phase II ","series":"Contracted","date":2015.0,"imdb":5.1},{"title_clean":"Crank ","series":"Crank","date":2006.0,"imdb":6.9},{"title_clean":"Crank: High Voltage ","series":"Crank","date":2009.0,"imdb":6.2},{"title_clean":"Crocodile ","series":"Crocodile","date":2000.0,"imdb":3.8},{"title_clean":"Crocodile 2: Death Swamp ","series":"Crocodile","date":2002.0,"imdb":3.7},{"title_clean":"Crouching Tiger, Hidden Dragon ","series":"Crouching Tiger, Hidden Dragon","date":2000.0,"imdb":7.8},{"title_clean":"Crouching Tiger, Hidden Dragon: Sword of Destiny ","series":"Crouching Tiger, Hidden Dragon","date":2016.0,"imdb":6.1},{"title_clean":"Da Vinci's War ","series":"Da Vinci's War","date":1993.0,"imdb":4.5},{"title_clean":"To the Limit ","series":"Da Vinci's War","date":1995.0,"imdb":3.1},{"title_clean":"Daddy's Home ","series":"Daddy's Home","date":2015.0,"imdb":6.2},{"title_clean":"Daddy's Home 2 ","series":"Daddy's Home","date":2017.0,"imdb":6.0},{"title_clean":"Daredevil ","series":"Daredevil","date":2003.0,"imdb":5.3},{"title_clean":"Elektra ","series":"Daredevil","date":2005.0,"imdb":4.7},{"title_clean":"Darling ","series":"Darling","date":2015.0,"imdb":5.5},{"title_clean":"Darling 2 ","series":"Darling","date":2016.0,"imdb":4.0},{"title_clean":"Heaven's Prisoners ","series":"Dave Robicheaux","date":1996.0,"imdb":5.8},{"title_clean":"In the Electric Mist ","series":"Dave Robicheaux","date":2009.0,"imdb":6.1},{"title_clean":"The Dead ","series":"The Dead","date":2010.0,"imdb":5.7},{"title_clean":"The Dead 2: India ","series":"The Dead","date":2013.0,"imdb":5.1},{"title_clean":"Dead in Tombstone ","series":"Dead in Tombstone","date":2013.0,"imdb":4.9},{"title_clean":"Dead Again in Tombstone ","series":"Dead in Tombstone","date":2017.0,"imdb":4.3},{"title_clean":"Dead Rising: Watchtower ","series":"Dead Rising","date":2015.0,"imdb":5.2},{"title_clean":"Dead Rising: Endgame ","series":"Dead Rising","date":2016.0,"imdb":4.7},{"title_clean":"Decadent Evil ","series":"Decadent Evil","date":2005.0,"imdb":3.8},{"title_clean":"Decadent Evil II ","series":"Decadent Evil","date":2007.0,"imdb":3.7},{"title_clean":"Deccal ","series":"Deccal","date":2015.0,"imdb":3.0},{"title_clean":"Deccal 2 ","series":"Deccal","date":2017.0,"imdb":4.2},{"title_clean":"Decoys ","series":"Decoys","date":2004.0,"imdb":4.6},{"title_clean":"Decoys 2: Alien Seduction ","series":"Decoys","date":2007.0,"imdb":4.6},{"title_clean":"Deep Blue Sea ","series":"Deep Blue Sea","date":1999.0,"imdb":5.9},{"title_clean":"Deep Blue Sea 2 ","series":"Deep Blue Sea","date":2018.0,"imdb":3.3},{"title_clean":"Demolition High ","series":"Demolition High","date":1996.0,"imdb":4.7},{"title_clean":"Demolition University ","series":"Demolition High","date":1997.0,"imdb":3.9},{"title_clean":"The Descent ","series":"The Descent","date":2005.0,"imdb":7.2},{"title_clean":"The Descent: Part 2 ","series":"The Descent","date":2009.0,"imdb":5.8},{"title_clean":"Desperadas ","series":"Desperadas","date":2008.0,"imdb":6.5},{"title_clean":"Desperadas 2 ","series":"Desperadas","date":2008.0,"imdb":6.5},{"title_clean":"Detective Chinatown ","series":"Detective Chinatown","date":2015.0,"imdb":6.6},{"title_clean":"Detective Chinatown 2 ","series":"Detective Chinatown","date":2018.0,"imdb":6.0},{"title_clean":"Deuce Bigalow: Male Gigolo ","series":"Deuce Bigalow","date":1999.0,"imdb":5.7},{"title_clean":"Deuce Bigalow: European Gigolo ","series":"Deuce Bigalow","date":2005.0,"imdb":4.7},{"title_clean":"Devil in the Flesh ","series":"Devil in the Flesh","date":1998.0,"imdb":5.3},{"title_clean":"Devil in the Flesh 2 ","series":"Devil in the Flesh","date":2000.0,"imdb":4.4},{"title_clean":"Doll Graveyard ","series":"Doll Graveyard","date":2005.0,"imdb":4.1},{"title_clean":"Ooga Booga ","series":"Doll Graveyard","date":2013.0,"imdb":3.5},{"title_clean":"Don ","series":"Don","date":2006.0,"imdb":7.2},{"title_clean":"Don 2 ","series":"Don","date":2011.0,"imdb":7.1},{"title_clean":"Donnie Darko ","series":"Donnie Darko","date":2001.0,"imdb":8.0},{"title_clean":"S. Darko ","series":"Donnie Darko","date":2009.0,"imdb":3.6},{"title_clean":"Don't Go Breaking My Heart ","series":"Don't Go Breaking My Heart","date":2011.0,"imdb":6.5},{"title_clean":"Don't Go Breaking My Heart 2 ","series":"Don't Go Breaking My Heart","date":2014.0,"imdb":5.5},{"title_clean":"D\u00fc\u011f\u00fcn Dernek ","series":"D\u00fc\u011f\u00fcn Dernek","date":2013.0,"imdb":7.1},{"title_clean":"D\u00fc\u011f\u00fcn Dernek 2: S\u00fcnnet ","series":"D\u00fc\u011f\u00fcn Dernek","date":2015.0,"imdb":6.5},{"title_clean":"The Dukes of Hazzard: Reunion! ","series":"The Dukes of Hazzard (1997 series) *","date":1997.0,"imdb":6.5},{"title_clean":"The Dukes of Hazzard: Hazzard in Hollywood ","series":"The Dukes of Hazzard (1997 series) *","date":2000.0,"imdb":6.0},{"title_clean":"The Dukes of Hazzard ","series":"The Dukes of Hazzard (2005 series)","date":2005.0,"imdb":5.1},{"title_clean":"The Dukes of Hazzard: The Beginning ","series":"The Dukes of Hazzard (2005 series)","date":2007.0,"imdb":4.5},{"title_clean":"Election ","series":"Election","date":2005.0,"imdb":7.1},{"title_clean":"Election 2 ","series":"Election","date":2006.0,"imdb":7.4},{"title_clean":"Elizabeth ","series":"Elizabeth","date":1998.0,"imdb":7.4},{"title_clean":"Elizabeth: The Golden Age ","series":"Elizabeth","date":2007.0,"imdb":6.8},{"title_clean":"The Emperor's New Groove ","series":"The Emperor's New Groove","date":2000.0,"imdb":7.3},{"title_clean":"Kronk's New Groove ","series":"The Emperor's New Groove","date":2005.0,"imdb":5.8},{"title_clean":"Enthiran ","series":"Enthiran","date":2010.0,"imdb":7.1},{"title_clean":"2.0 ","series":"Enthiran","date":2018.0,"imdb":6.3},{"title_clean":"Epoch ","series":"Epoch","date":2001.0,"imdb":4.9},{"title_clean":"Epoch: Evolution ","series":"Epoch","date":2003.0,"imdb":4.3},{"title_clean":"The Equalizer ","series":"The Equalizer *","date":2014.0,"imdb":7.2},{"title_clean":"The Equalizer 2 ","series":"The Equalizer *","date":2018.0,"imdb":6.7},{"title_clean":"The Fall of the Essex Boys ","series":"Essex Boys","date":2013.0,"imdb":3.8},{"title_clean":"Essex Boys: Retribution ","series":"Essex Boys","date":2013.0,"imdb":4.1},{"title_clean":"Even Hitler Had a Girlfriend ","series":"Even Hitler Had a Girlfriend","date":1992.0,"imdb":5.5},{"title_clean":"The Hitler Tapes ","series":"Even Hitler Had a Girlfriend","date":1994.0,"imdb":4.5},{"title_clean":"Excessive Force ","series":"Excessive Force","date":1993.0,"imdb":5.3},{"title_clean":"Excessive Force II: Force on Force ","series":"Excessive Force","date":1995.0,"imdb":4.3},{"title_clean":"The Farm: Angola, USA ","series":"The Farm","date":1998.0,"imdb":7.6},{"title_clean":"The Farm: 10 Down ","series":"The Farm","date":2009.0,"imdb":6.8},{"title_clean":"Fast Getaway ","series":"Fast Getaway","date":1991.0,"imdb":5.4},{"title_clean":"Fast Getaway II ","series":"Fast Getaway","date":1994.0,"imdb":4.6},{"title_clean":"Father of the Bride ","series":"Father of the Bride (1991 series)","date":1991.0,"imdb":6.5},{"title_clean":"Father of the Bride Part II ","series":"Father of the Bride (1991 series)","date":1995.0,"imdb":6.0},{"title_clean":"The Fear ","series":"The Fear","date":1995.0,"imdb":3.5},{"title_clean":"The Fear: Resurrection ","series":"The Fear","date":1999.0,"imdb":2.9},{"title_clean":"FernGully: The Last Rainforest ","series":"FernGully","date":1992.0,"imdb":6.5},{"title_clean":"FernGully 2: The Magical Rescue ","series":"FernGully","date":1998.0,"imdb":4.5},{"title_clean":"Final Option ","series":"Final Option","date":1994.0,"imdb":6.0},{"title_clean":"First Option ","series":"Final Option","date":1996.0,"imdb":5.9},{"title_clean":"Fist of Legend ","series":"Fist of Legend","date":1994.0,"imdb":7.5},{"title_clean":"Legend of the Fist: The Return of Chen Zhen' ","series":"Fist of Legend","date":2010.0,"imdb":6.3},{"title_clean":"The Flintstones ","series":"The Flintstones (Theatrical films)","date":1994.0,"imdb":4.9},{"title_clean":"The Flintstones in Viva Rock Vegas ","series":"The Flintstones (Theatrical films)","date":2000.0,"imdb":3.6},{"title_clean":"Frame-Up ","series":"Frame-Up","date":1991.0,"imdb":4.4},{"title_clean":"Frame-Up II: The Cover-Up ","series":"Frame-Up","date":1994.0,"imdb":3.9},{"title_clean":"Freeway ","series":"Freeway","date":1996.0,"imdb":6.8},{"title_clean":"Freeway II: Confessions of a Trickbaby ","series":"Freeway","date":1999.0,"imdb":5.7},{"title_clean":"Frozen ","series":"Frozen","date":2013.0,"imdb":7.4},{"title_clean":"Frozen II ","series":"Frozen","date":2019.0,"imdb":6.9},{"title_clean":"The Fugitive ","series":"The Fugitive","date":1993.0,"imdb":7.8},{"title_clean":"US Marshals ","series":"The Fugitive","date":1998.0,"imdb":6.6},{"title_clean":"Fukrey ","series":"Fukrey","date":2013.0,"imdb":6.9},{"title_clean":"Fukrey Returns ","series":"Fukrey","date":2017.0,"imdb":6.5},{"title_clean":"Fullmetal Alchemist the Movie: Conqueror of Shamballa ","series":"Fullmetal Alchemist","date":2005.0,"imdb":7.4},{"title_clean":"Fullmetal Alchemist: The Sacred Star of Milos ","series":"Fullmetal Alchemist","date":2011.0,"imdb":7.0},{"title_clean":"Gaayam ","series":"Gaayam","date":1993.0,"imdb":7.3},{"title_clean":"Gaayam 2 ","series":"Gaayam","date":2010.0,"imdb":5.2},{"title_clean":"Galaxis ","series":"Galaxis","date":1995.0,"imdb":3.3},{"title_clean":"The Survivor ","series":"Galaxis","date":1998.0,"imdb":3.4},{"title_clean":"Garfield ","series":"Garfield *","date":2004.0,"imdb":5.0},{"title_clean":"Garfield: A Tail of Two Kitties ","series":"Garfield *","date":2006.0,"imdb":5.0},{"title_clean":"The Gathering Storm ","series":"The Gathering Storm","date":2002.0,"imdb":7.5},{"title_clean":"Into the Storm ","series":"The Gathering Storm","date":2009.0,"imdb":7.1},{"title_clean":"Genius Party ","series":"Genius Party","date":2007.0,"imdb":7.1},{"title_clean":"Genius Party Beyond ","series":"Genius Party","date":2008.0,"imdb":7.1},{"title_clean":"George of the Jungle ","series":"George of the Jungle *","date":1997.0,"imdb":5.5},{"title_clean":"George of the Jungle 2 ","series":"George of the Jungle *","date":2003.0,"imdb":3.3},{"title_clean":"Get Smart ","series":"Get Smart (2008 series)","date":2008.0,"imdb":6.5},{"title_clean":"Get Smart's Bruce and Lloyd: Out of Control ","series":"Get Smart (2008 series)","date":2008.0,"imdb":4.9},{"title_clean":"Gettysburg ","series":"Gettysburg","date":1993.0,"imdb":7.6},{"title_clean":"Gods and Generals ","series":"Gettysburg","date":2003.0,"imdb":6.4},{"title_clean":"Ghost Rider ","series":"Ghost Rider","date":2007.0,"imdb":5.2},{"title_clean":"Ghost Rider: Spirit of Vengeance ","series":"Ghost Rider","date":2011.0,"imdb":4.3},{"title_clean":"G.I. Joe: The Rise of Cobra ","series":"G.I. Joe","date":2009.0,"imdb":5.8},{"title_clean":"G.I. Joe: Retaliation ","series":"G.I. Joe","date":2013.0,"imdb":5.8},{"title_clean":"Girlfriends' Getaway ","series":"Girlfriends' Getaway","date":2014.0,"imdb":6.8},{"title_clean":"Girlfriends' Getaway 2 ","series":"Girlfriends' Getaway","date":2015.0,"imdb":6.4},{"title_clean":"The Glass House ","series":"The Glass House","date":2001.0,"imdb":5.8},{"title_clean":"Glass House: The Good Mother ","series":"The Glass House","date":2006.0,"imdb":5.6},{"title_clean":"Gnomeo & Juliet ","series":"Gnomeo & Juliet","date":2011.0,"imdb":5.9},{"title_clean":"Sherlock Gnomes ","series":"Gnomeo & Juliet","date":2018.0,"imdb":5.2},{"title_clean":"Goli Soda ","series":"Goli Soda","date":2014.0,"imdb":7.7},{"title_clean":"Goli Soda 2 ","series":"Goli Soda","date":2018.0,"imdb":7.3},{"title_clean":"A Goofy Movie ","series":"Goof Troop (A)*","date":1995.0,"imdb":6.8},{"title_clean":"An Extremely Goofy Movie ","series":"Goof Troop (A)*","date":2000.0,"imdb":6.4},{"title_clean":"Goon ","series":"Goon","date":2011.0,"imdb":6.8},{"title_clean":"Goon: Last of the Enforcers ","series":"Goon","date":2017.0,"imdb":5.8},{"title_clean":"Granny Boom ","series":"Granny","date":2005.0,"imdb":5.9},{"title_clean":"Supergranny.com ","series":"Granny","date":2007.0,"imdb":5.4},{"title_clean":"Grave Encounters ","series":"Grave Encounters","date":2011.0,"imdb":6.1},{"title_clean":"Grave Encounters 2 ","series":"Grave Encounters","date":2012.0,"imdb":5.1},{"title_clean":"Planet Terror ","series":"Grindhouse","date":2007.0,"imdb":7.1},{"title_clean":"Death Proof ","series":"Grindhouse","date":2007.0,"imdb":7.0},{"title_clean":"The Growing Pains Movie ","series":"Growing Pains *","date":2000.0,"imdb":5.2},{"title_clean":"Growing Pains: Return of the Seavers ","series":"Growing Pains *","date":2004.0,"imdb":4.4},{"title_clean":"Grown Ups ","series":"Grown Ups","date":2010.0,"imdb":5.9},{"title_clean":"Grown Ups 2 ","series":"Grown Ups","date":2013.0,"imdb":5.4},{"title_clean":"Grumpy Old Men ","series":"Grumpy Old Men","date":1993.0,"imdb":7.0},{"title_clean":"Grumpier Old Men ","series":"Grumpy Old Men","date":1995.0,"imdb":6.7},{"title_clean":"Der gute Bulle ","series":"Der gute Bulle","date":2017.0,"imdb":5.8},{"title_clean":"Der gute Bulle: Friss oder stirb ","series":"Der gute Bulle","date":2019.0,"imdb":6.2},{"title_clean":"Guwapings: The First Adventure ","series":"Guwapings","date":1992.0,"imdb":6.4},{"title_clean":"Guwapings dos ","series":"Guwapings","date":1993.0,"imdb":5.1},{"title_clean":"The Guyver ","series":"Guyver","date":1991.0,"imdb":5.0},{"title_clean":"Guyver: Dark Hero ","series":"Guyver","date":1994.0,"imdb":6.0},{"title_clean":"Half Past Dead ","series":"Half Past Dead","date":2002.0,"imdb":4.7},{"title_clean":"Half Past Dead 2 ","series":"Half Past Dead","date":2007.0,"imdb":4.4},{"title_clean":"Halloween ","series":"Halloween (2007 series)","date":2007.0,"imdb":6.1},{"title_clean":"Halloween II ","series":"Halloween (2007 series)","date":2009.0,"imdb":4.9},{"title_clean":"Hansel & Gretel ","series":"Hansel & Gretel","date":2013.0,"imdb":2.8},{"title_clean":"Hansel vs Gretel ","series":"Hansel & Gretel","date":2015.0,"imdb":2.9},{"title_clean":"Happiness ","series":"Happiness","date":1998.0,"imdb":7.7},{"title_clean":"Life During Wartime ","series":"Happiness","date":2009.0,"imdb":6.4},{"title_clean":"Happy Death Day ","series":"Happy Death Day","date":2017.0,"imdb":6.5},{"title_clean":"Happy Death Day 2U ","series":"Happy Death Day","date":2019.0,"imdb":6.2},{"title_clean":"Happy Feet ","series":"Happy Feet","date":2006.0,"imdb":6.4},{"title_clean":"Happy Feet Two ","series":"Happy Feet","date":2011.0,"imdb":5.9},{"title_clean":"Hard Target ","series":"Hard Target","date":1993.0,"imdb":6.2},{"title_clean":"Hard Target 2 ","series":"Hard Target","date":2016.0,"imdb":5.3},{"title_clean":"Harriet the Spy ","series":"Harriet the Spy","date":1996.0,"imdb":5.9},{"title_clean":"Harriet the Spy: Blog Wars ","series":"Harriet the Spy","date":2010.0,"imdb":4.7},{"title_clean":"Harry & Meghan: A Royal Romance ","series":"Harry & Meghan","date":2018.0,"imdb":5.7},{"title_clean":"Harry & Meghan: Becoming Royal ","series":"Harry & Meghan","date":2019.0,"imdb":5.2},{"title_clean":"The Haunting in Connecticut ","series":"The Haunting in Connecticut","date":2009.0,"imdb":5.9},{"title_clean":"The Haunting in Connecticut 2: Ghosts of Georgia ","series":"The Haunting in Connecticut","date":2013.0,"imdb":5.3},{"title_clean":"Hatta Ishaar Akhar ","series":"Hatta Ishaar Akhar","date":1994.0,"imdb":6.0},{"title_clean":"Ha\u00effa ","series":"Hatta Ishaar Akhar","date":1996.0,"imdb":6.2},{"title_clean":"He Who Dares ","series":"He Who Dares","date":2014.0,"imdb":3.0},{"title_clean":"He Who Dares: Downing Street Siege ","series":"He Who Dares","date":2014.0,"imdb":2.8},{"title_clean":"Hellboy ","series":"Hellboy","date":2004.0,"imdb":6.8},{"title_clean":"Hellboy II: The Golden Army ","series":"Hellboy","date":2008.0,"imdb":7.0},{"title_clean":"Henry Fool ","series":"Henry Fool & Fay Grim","date":1997.0,"imdb":7.2},{"title_clean":"Fay Grim ","series":"Henry Fool & Fay Grim","date":2006.0,"imdb":6.2},{"title_clean":"Hera Pheri ","series":"Hera Pheri","date":2000.0,"imdb":8.2},{"title_clean":"Phir Hera Pheri ","series":"Hera Pheri","date":2006.0,"imdb":6.8},{"title_clean":"Hercules ","series":"Disney's Hercules *","date":1997.0,"imdb":7.3},{"title_clean":"Hercules: Zero to Hero ","series":"Disney's Hercules *","date":1999.0,"imdb":6.5},{"title_clean":"The Heroic Trio ","series":"The Heroic Trio","date":1993.0,"imdb":6.5},{"title_clean":"Executioners ","series":"The Heroic Trio","date":1993.0,"imdb":5.8},{"title_clean":"Hey Arnold! The Movie ","series":"Hey Arnold! *","date":2002.0,"imdb":6.0},{"title_clean":"Hey Arnold!: The Jungle Movie ","series":"Hey Arnold! *","date":2017.0,"imdb":7.6},{"title_clean":"The Hills Have Eyes ","series":"The Hills Have Eyes (2006 series)","date":2006.0,"imdb":6.4},{"title_clean":"The Hills Have Eyes 2 ","series":"The Hills Have Eyes (2006 series)","date":2007.0,"imdb":5.1},{"title_clean":"Hollywood Dreams ","series":"Hollywood Dreams","date":1994.0,"imdb":2.4},{"title_clean":"Hollywood Dreams Take 2 ","series":"Hollywood Dreams","date":1995.0,"imdb":2.8},{"title_clean":"Home Along da Riles da Movie ","series":"Home Along da Riles","date":1993.0,"imdb":6.5},{"title_clean":"Home Along da Riles 2 ","series":"Home Along da Riles","date":1997.0,"imdb":6.2},{"title_clean":"Homeward Bound: The Incredible Journey ","series":"Homeward Bound","date":1993.0,"imdb":6.9},{"title_clean":"Homeward Bound II: Lost in San Francisco ","series":"Homeward Bound","date":1996.0,"imdb":6.0},{"title_clean":"Horrible Bosses ","series":"Horrible Bosses","date":2011.0,"imdb":6.9},{"title_clean":"Horrible Bosses 2 ","series":"Horrible Bosses","date":2014.0,"imdb":6.3},{"title_clean":"Hot Shots! ","series":"Hot Shots!","date":1991.0,"imdb":6.8},{"title_clean":"Hot Shots! Part Deux ","series":"Hot Shots!","date":1993.0,"imdb":6.6},{"title_clean":"Hot Tub Time Machine ","series":"Hot Tub Time Machine","date":2010.0,"imdb":6.4},{"title_clean":"Hot Tub Time Machine 2 ","series":"Hot Tub Time Machine","date":2015.0,"imdb":5.1},{"title_clean":"House of the Dead ","series":"House of the Dead","date":2003.0,"imdb":2.0},{"title_clean":"House of the Dead 2 ","series":"House of the Dead","date":2005.0,"imdb":3.7},{"title_clean":"House on Haunted Hill ","series":"House on Haunted Hill","date":1999.0,"imdb":5.6},{"title_clean":"Return to House on Haunted Hill ","series":"House on Haunted Hill","date":2007.0,"imdb":4.6},{"title_clean":"The Houses October Built ","series":"The Houses October Built","date":2014.0,"imdb":5.2},{"title_clean":"The Houses October Built 2 ","series":"The Houses October Built","date":2017.0,"imdb":5.1},{"title_clean":"How High ","series":"How High","date":2001.0,"imdb":6.3},{"title_clean":"How High 2 ","series":"How High","date":2019.0,"imdb":2.9},{"title_clean":"Hulk Vs ","series":"Hulk (Marvel Animated Universe) (A)","date":2009.0,"imdb":7.0},{"title_clean":"Planet Hulk ","series":"Hulk (Marvel Animated Universe) (A)","date":2010.0,"imdb":6.8},{"title_clean":"Snow White and the Huntsman ","series":"The Huntsman","date":2012.0,"imdb":6.1},{"title_clean":"The Huntsman: Winter's War ","series":"The Huntsman","date":2016.0,"imdb":6.1},{"title_clean":"I Not Stupid ","series":"I Not Stupid","date":2002.0,"imdb":7.2},{"title_clean":"I Not Stupid Too ","series":"I Not Stupid","date":2006.0,"imdb":6.8},{"title_clean":"Ice Cream ","series":"Ice Cream","date":2014.0,"imdb":3.8},{"title_clean":"Ice Cream 2 ","series":"Ice Cream","date":2014.0,"imdb":3.8},{"title_clean":"Iceman ","series":"Iceman","date":2014.0,"imdb":4.8},{"title_clean":"Iceman: The Time Traveller ","series":"Iceman","date":2018.0,"imdb":3.8},{"title_clean":"If These Walls Could Talk ","series":"If These Walls Could Talk","date":1996.0,"imdb":7.0},{"title_clean":"If These Walls Could Talk 2 ","series":"If These Walls Could Talk","date":2000.0,"imdb":7.1},{"title_clean":"If You Are the One ","series":"If You Are the One","date":2008.0,"imdb":6.8},{"title_clean":"If You Are the One 2 ","series":"If You Are the One","date":2010.0,"imdb":5.9},{"title_clean":"The Incredibles ","series":"The Incredibles","date":2004.0,"imdb":8.0},{"title_clean":"Incredibles 2 ","series":"The Incredibles","date":2018.0,"imdb":7.6},{"title_clean":"Independence Day ","series":"Independence Day","date":1996.0,"imdb":7.0},{"title_clean":"Independence Day: Resurgence ","series":"Independence Day","date":2016.0,"imdb":5.2},{"title_clean":"Inside Man ","series":"Inside Man","date":2006.0,"imdb":7.6},{"title_clean":"Inside Man: Most Wanted ","series":"Inside Man","date":2019.0,"imdb":5.6},{"title_clean":"Inspector Gadget ","series":"Inspector Gadget (1999 series) *","date":1999.0,"imdb":4.1},{"title_clean":"Inspector Gadget 2 ","series":"Inspector Gadget (1999 series) *","date":2003.0,"imdb":3.4},{"title_clean":"Interceptor Force ","series":"Interceptor Force","date":1999.0,"imdb":3.9},{"title_clean":"Interceptor Force 2 ","series":"Interceptor Force","date":2002.0,"imdb":4.0},{"title_clean":"Into the Blue ","series":"Into the Blue","date":2005.0,"imdb":5.9},{"title_clean":"Into the Blue 2: The Reef ","series":"Into the Blue","date":2009.0,"imdb":4.7},{"title_clean":"Iron Monkey ","series":"Iron Monkey","date":1993.0,"imdb":7.5},{"title_clean":"Iron Monkey 2 ","series":"Iron Monkey","date":1996.0,"imdb":4.6},{"title_clean":"Iron Sky ","series":"Iron Sky","date":2012.0,"imdb":5.9},{"title_clean":"Iron Sky: The Coming Race ","series":"Iron Sky","date":2019.0,"imdb":5.0},{"title_clean":"It ","series":"It","date":2017.0,"imdb":7.3},{"title_clean":"It: Chapter Two ","series":"It","date":2019.0,"imdb":6.6},{"title_clean":"Jack Reacher ","series":"Jack Reacher","date":2012.0,"imdb":7.0},{"title_clean":"Jack Reacher: Never Go Back ","series":"Jack Reacher","date":2016.0,"imdb":6.1},{"title_clean":"Jannat ","series":"Jannat","date":2008.0,"imdb":6.9},{"title_clean":"Jannat 2 ","series":"Jannat","date":2012.0,"imdb":6.1},{"title_clean":"Jatt & Juliet ","series":"Jatt & Juliet","date":2012.0,"imdb":7.5},{"title_clean":"Jatt & Juliet 2 ","series":"Jatt & Juliet","date":2013.0,"imdb":7.5},{"title_clean":"Jawani Phir Nahi Ani ","series":"Jawani Phir Nahi Ani","date":2015.0,"imdb":7.6},{"title_clean":"Jawani Phir Nahi Ani 2 ","series":"Jawani Phir Nahi Ani","date":2018.0,"imdb":7.6},{"title_clean":"Jingle All the Way ","series":"Jingle All the Way","date":1996.0,"imdb":5.6},{"title_clean":"Jingle All the Way 2 ","series":"Jingle All the Way","date":2014.0,"imdb":3.8},{"title_clean":"Jism ","series":"Jism","date":2003.0,"imdb":5.2},{"title_clean":"Jism 2 ","series":"Jism","date":2012.0,"imdb":3.0},{"title_clean":"Jithan ","series":"Jithan","date":2005.0,"imdb":5.9},{"title_clean":"Jithan 2 ","series":"Jithan","date":2016.0,"imdb":3.3},{"title_clean":"Jeannette: The Childhood of Joan of Arc ","series":"Joan of Arc","date":2017.0,"imdb":5.7},{"title_clean":"Joan of Arc ","series":"Joan of Arc","date":2019.0,"imdb":5.8},{"title_clean":"Joe Dirt ","series":"Joe Dirt","date":2001.0,"imdb":6.0},{"title_clean":"Joe Dirt 2: Beautiful Loser ","series":"Joe Dirt","date":2015.0,"imdb":4.2},{"title_clean":"Johnny Tsunami ","series":"Johnny series","date":1999.0,"imdb":6.3},{"title_clean":"Johnny Kapahala: Back on Board ","series":"Johnny series","date":2007.0,"imdb":5.5},{"title_clean":"Jolly LLB ","series":"Jolly LLB","date":2013.0,"imdb":7.5},{"title_clean":"Jolly LLB 2 ","series":"Jolly LLB","date":2017.0,"imdb":7.2},{"title_clean":"The Foreigner ","series":"Jonathan Cold","date":2003.0,"imdb":3.4},{"title_clean":"Black Dawn ","series":"Jonathan Cold","date":2005.0,"imdb":3.8},{"title_clean":"Journey to the Center of the Earth ","series":"Journey series","date":2008.0,"imdb":5.8},{"title_clean":"Journey 2: The Mysterious Island ","series":"Journey series","date":2012.0,"imdb":5.8},{"title_clean":"Julie ","series":"Julie","date":2004.0,"imdb":4.1},{"title_clean":"Julie 2 ","series":"Julie","date":2017.0,"imdb":2.4},{"title_clean":"21 Jump Street ","series":"Jump Street","date":2012.0,"imdb":7.2},{"title_clean":"22 Jump Street ","series":"Jump Street","date":2014.0,"imdb":7.0},{"title_clean":"Kahaani ","series":"Kahaani","date":2012.0,"imdb":8.1},{"title_clean":"Kahaani 2 ","series":"Kahaani","date":2016.0,"imdb":6.6},{"title_clean":"Kalakalappu ","series":"Kalakalappu","date":2012.0,"imdb":6.9},{"title_clean":"Kalakalappu 2 ","series":"Kalakalappu","date":2018.0,"imdb":4.9},{"title_clean":"Kalavani ","series":"Kalavani","date":2010.0,"imdb":7.1},{"title_clean":"Kalavani 2 ","series":"Kalavani","date":2019.0,"imdb":5.2},{"title_clean":"Kalle Blomkvist - M\u00e4sterdetektiven lever farligt ","series":"Kalle Blomkvist","date":1996.0,"imdb":5.9},{"title_clean":"Kalle Blomkvist och Rasmus ","series":"Kalle Blomkvist","date":1997.0,"imdb":5.5},{"title_clean":"Kalpana ","series":"Kalpana","date":2012.0,"imdb":6.1},{"title_clean":"Kalpana 2 ","series":"Kalpana","date":2016.0,"imdb":5.7},{"title_clean":"Kangaroo Jack ","series":"Kangaroo Jack (a)","date":2003.0,"imdb":4.4},{"title_clean":"Kangaroo Jack: G'Day U.S.A.! ","series":"Kangaroo Jack (a)","date":2004.0,"imdb":4.0},{"title_clean":"Kazhugu ","series":"Kazhugu","date":2012.0,"imdb":6.2},{"title_clean":"Kazhugu 2 ","series":"Kazhugu","date":2019.0,"imdb":5.2},{"title_clean":"Good Burger ","series":"Kenan & Kel **","date":1997.0,"imdb":5.7},{"title_clean":"Two Heads Are Better Than None ","series":"Kenan & Kel **","date":2000.0,"imdb":7.8},{"title_clean":"Khmel - Film pervyy: Krepost ","series":"Khmel","date":1991.0,"imdb":6.6},{"title_clean":"Khmel - Film vtoroy: Iskhod ","series":"Khmel","date":1991.0,"imdb":6.3},{"title_clean":"Kick ","series":"Kick","date":2009.0,"imdb":7.8},{"title_clean":"Kick 2 ","series":"Kick","date":2015.0,"imdb":5.1},{"title_clean":"Kick-Ass ","series":"Kick-Ass","date":2010.0,"imdb":7.6},{"title_clean":"Kick-Ass 2 ","series":"Kick-Ass","date":2013.0,"imdb":6.5},{"title_clean":"Kickboxer: Vengeance ","series":"Kickboxer","date":2016.0,"imdb":4.9},{"title_clean":"Kickboxer: Retaliation ","series":"Kickboxer","date":2018.0,"imdb":5.0},{"title_clean":"A Kid in King Arthur's Court ","series":"A Kid in...","date":1995.0,"imdb":4.7},{"title_clean":"A Kid in Aladdin's Palace ","series":"A Kid in...","date":1997.0,"imdb":5.3},{"title_clean":"Kiler ","series":"Kiler","date":1997.0,"imdb":7.6},{"title_clean":"Kiler\u00f3w 2-\u00f3ch ","series":"Kiler","date":1999.0,"imdb":6.7},{"title_clean":"Killer Nerd ","series":"Killer Nerd","date":1991.0,"imdb":4.1},{"title_clean":"Bride of Killer Nerd ","series":"Killer Nerd","date":1992.0,"imdb":4.5},{"title_clean":"Klinkevals ","series":"Klinkevals","date":1999.0,"imdb":5.5},{"title_clean":"Juliane ","series":"Klinkevals","date":2000.0,"imdb":5.8},{"title_clean":"Knocked Up ","series":"Knocked Up","date":2007.0,"imdb":6.9},{"title_clean":"This Is 40 ","series":"Knocked Up","date":2012.0,"imdb":6.2},{"title_clean":"Kokow\u00e4\u00e4h ","series":"Kokow\u00e4\u00e4h","date":2011.0,"imdb":6.3},{"title_clean":"Kokow\u00e4\u00e4h 2 ","series":"Kokow\u00e4\u00e4h","date":2013.0,"imdb":5.4},{"title_clean":"Curse of the Komodo ","series":"Komodo","date":2004.0,"imdb":2.8},{"title_clean":"Komodo vs. Cobra ","series":"Komodo","date":2005.0,"imdb":2.7},{"title_clean":"The Rise of the Krays ","series":"The Krays","date":2015.0,"imdb":4.9},{"title_clean":"The Fall of the Krays ","series":"The Krays","date":2016.0,"imdb":4.4},{"title_clean":"The Devil's Whore ","series":" The Ladies Fanshawe","date":2008.0,"imdb":7.1},{"title_clean":"New Worlds ","series":" The Ladies Fanshawe","date":2014.0,"imdb":6.3},{"title_clean":"Lady Dragon ","series":"Lady Dragon","date":1992.0,"imdb":5.1},{"title_clean":"Lady Dragon 2 ","series":"Lady Dragon","date":1993.0,"imdb":4.5},{"title_clean":"Laid to Rest ","series":"Laid to Rest","date":2009.0,"imdb":5.3},{"title_clean":"ChromeSkull: Laid to Rest 2 ","series":"Laid to Rest","date":2011.0,"imdb":5.1},{"title_clean":"Lap Dancing ","series":"Lap Dancing","date":1995.0,"imdb":4.5},{"title_clean":"Confessions of a Lap Dancer ","series":"Lap Dancing","date":1997.0,"imdb":5.3},{"title_clean":"The Last Kiss ","series":"The Last Kiss","date":2001.0,"imdb":6.9},{"title_clean":"Kiss Me Again ","series":"The Last Kiss","date":2010.0,"imdb":5.9},{"title_clean":"The Last Seduction ","series":"The Last Seduction","date":1994.0,"imdb":7.0},{"title_clean":"The Last Seduction II ","series":"The Last Seduction","date":1999.0,"imdb":4.4},{"title_clean":"The Lawnmower Man ","series":"The Lawnmower Man","date":1992.0,"imdb":5.5},{"title_clean":"Lawnmower Man 2: Beyond Cyberspace ","series":"The Lawnmower Man","date":1996.0,"imdb":2.5},{"title_clean":"Leapin' Leprechauns ","series":"Leapin' Leprechauns","date":1995.0,"imdb":4.3},{"title_clean":"Spellbreaker: Secret of the Leprechauns ","series":"Leapin' Leprechauns","date":1996.0,"imdb":3.6},{"title_clean":"Lee Rock ","series":"Lee Rock","date":1991.0,"imdb":7.1},{"title_clean":"Lee Rock II ","series":"Lee Rock","date":1991.0,"imdb":6.7},{"title_clean":"The Legend of the North Wind ","series":"The Legend of the North Wind (A) *","date":1992.0,"imdb":7.1},{"title_clean":"The Return of the North Wind ","series":"The Legend of the North Wind (A) *","date":1994.0,"imdb":7.8},{"title_clean":"Like Mike ","series":"Like Mike","date":2002.0,"imdb":5.3},{"title_clean":"Like Mike 2: Streetball ","series":"Like Mike","date":2006.0,"imdb":4.1},{"title_clean":"The Little Polar Bear ","series":"The Little Polar Bear *(A)","date":2001.0,"imdb":5.9},{"title_clean":"The Little Polar Bear 2: The Mysterious Island ","series":"The Little Polar Bear *(A)","date":2005.0,"imdb":5.6},{"title_clean":"The Little Rascals ","series":"The Little Rascals","date":1994.0,"imdb":6.3},{"title_clean":"The Little Rascals Save the Day ","series":"The Little Rascals","date":2014.0,"imdb":5.1},{"title_clean":"The Living Forest ","series":"The Living Forest","date":2001.0,"imdb":5.2},{"title_clean":"Spirit of the Forest ","series":"The Living Forest","date":2008.0,"imdb":4.4},{"title_clean":"The Lost World ","series":"The Lost World","date":1992.0,"imdb":5.4},{"title_clean":"Return to the Lost World ","series":"The Lost World","date":1992.0,"imdb":5.1},{"title_clean":"Lotta p\u00e5 Br\u00e5kmakargatan ","series":"Lotta","date":1992.0,"imdb":5.8},{"title_clean":"Lotta 2 - Lotta flyttar hemifr\u00e5n ","series":"Lotta","date":1993.0,"imdb":5.8},{"title_clean":"Love is All ","series":"Love is All","date":2007.0,"imdb":7.0},{"title_clean":"Family Way ","series":"Love is All","date":2012.0,"imdb":6.6},{"title_clean":"Maari ","series":"Maari","date":2015.0,"imdb":6.2},{"title_clean":"Maari 2 ","series":"Maari","date":2018.0,"imdb":5.6},{"title_clean":"The Girl of Your Dreams ","series":"Macarena Granada","date":1998.0,"imdb":6.9},{"title_clean":"The Queen of Spain ","series":"Macarena Granada","date":2016.0,"imdb":5.1},{"title_clean":"MacGyver: Lost Treasure of Atlantis ","series":"MacGyver *","date":1994.0,"imdb":6.4},{"title_clean":"MacGyver: Trail to Doomsday ","series":"MacGyver *","date":1994.0,"imdb":6.3},{"title_clean":"Magic Mike ","series":"Magic Mike","date":2012.0,"imdb":6.1},{"title_clean":"Magic Mike XXL ","series":"Magic Mike","date":2015.0,"imdb":5.6},{"title_clean":"Maleficent ","series":"Maleficent","date":2014.0,"imdb":7.0},{"title_clean":"Maleficent: Mistress of Evil ","series":"Maleficent","date":2019.0,"imdb":6.6},{"title_clean":"Mamma Mia! ","series":"Mamma Mia!","date":2008.0,"imdb":6.4},{"title_clean":"Mamma Mia! Here We Go Again ","series":"Mamma Mia!","date":2018.0,"imdb":6.7},{"title_clean":"The Man with the Iron Fists ","series":"The Man with the Iron Fists","date":2012.0,"imdb":5.4},{"title_clean":"The Man with the Iron Fists 2 ","series":"The Man with the Iron Fists","date":2015.0,"imdb":4.4},{"title_clean":"Mand\u0131ra Filozofu ","series":"Mand\u0131ra Filozofu","date":2013.0,"imdb":6.8},{"title_clean":"Mand\u0131ra Filozofu \u0130stanbul ","series":"Mand\u0131ra Filozofu","date":2015.0,"imdb":5.8},{"title_clean":"Manje Bistre ","series":"Manje Bistre","date":2017.0,"imdb":6.6},{"title_clean":"Manje Bistre 2 ","series":"Manje Bistre","date":2019.0,"imdb":5.6},{"title_clean":"Manmadhudu ","series":"Manmadhudu","date":2002.0,"imdb":8.2},{"title_clean":"Manmadhudu 2 ","series":"Manmadhudu","date":2019.0,"imdb":4.9},{"title_clean":"Mantra ","series":"Mantra","date":2007.0,"imdb":6.9},{"title_clean":"Mantra 2 ","series":"Mantra","date":2013.0,"imdb":4.4},{"title_clean":"Mapado ","series":"Mapado","date":2005.0,"imdb":6.1},{"title_clean":"Mapado 2: Back to the Island ","series":"Mapado","date":2007.0,"imdb":5.8},{"title_clean":"Mardaani ","series":"Mardaani","date":2014.0,"imdb":7.3},{"title_clean":"Mardaani 2 ","series":"Mardaani","date":2019.0,"imdb":7.4},{"title_clean":"Maria Mariana ","series":"Maria Mariana","date":1996.0,"imdb":4.8},{"title_clean":"Maria Mariana II ","series":"Maria Mariana","date":1998.0,"imdb":5.1},{"title_clean":"The Mask ","series":"The Mask *","date":1994.0,"imdb":6.9},{"title_clean":"Son of the Mask ","series":"The Mask *","date":2005.0,"imdb":2.2},{"title_clean":"Max ","series":"Max","date":2015.0,"imdb":6.7},{"title_clean":"Max 2: White House Hero ","series":"Max","date":2017.0,"imdb":5.2},{"title_clean":"Max Havoc: Curse of the Dragon ","series":"Max Havoc","date":2004.0,"imdb":4.6},{"title_clean":"Max Havoc: Ring of Fire ","series":"Max Havoc","date":2006.0,"imdb":3.1},{"title_clean":"Mean Girls ","series":"Mean Girls","date":2004.0,"imdb":7.0},{"title_clean":"Mean Girls 2 ","series":"Mean Girls","date":2011.0,"imdb":4.1},{"title_clean":"The Mechanic ","series":"The Mechanic","date":2011.0,"imdb":6.6},{"title_clean":"Mechanic: Resurrection ","series":"The Mechanic","date":2016.0,"imdb":5.7},{"title_clean":"Hindi Medium ","series":"Medium","date":2017.0,"imdb":7.8},{"title_clean":"Angrezi Medium ","series":"Medium","date":2020.0,"imdb":7.3},{"title_clean":"Merlin ","series":"Merlin","date":1998.0,"imdb":7.1},{"title_clean":"Merlin's Apprentice ","series":"Merlin","date":2006.0,"imdb":5.3},{"title_clean":"The Messengers ","series":"The Messengers","date":2007.0,"imdb":5.4},{"title_clean":"Messengers 2: The Scarecrow ","series":"The Messengers","date":2009.0,"imdb":4.7},{"title_clean":"Horse Sense ","series":"Michael Woods & Tommy Biggs","date":1999.0,"imdb":6.2},{"title_clean":"Jumping Ship ","series":"Michael Woods & Tommy Biggs","date":2001.0,"imdb":6.2},{"title_clean":"Mickey's Once Upon a Christmas ","series":"Mickey's Once Upon a Christmas","date":1999.0,"imdb":7.2},{"title_clean":"Mickey's Twice Upon a Christmas ","series":"Mickey's Once Upon a Christmas","date":2004.0,"imdb":6.5},{"title_clean":"The Girl with the Dragon Tattoo ","series":"Millennium","date":2011.0,"imdb":7.8},{"title_clean":"The Girl in the Spider's Web ","series":"Millennium","date":2018.0,"imdb":6.1},{"title_clean":"Mindgame ","series":"Mindgame *","date":1998.0,"imdb":5.4},{"title_clean":"Mindgame Trilogy ","series":"Mindgame *","date":1999.0,"imdb":6.0},{"title_clean":"Mirrors ","series":"Mirrors","date":2008.0,"imdb":6.2},{"title_clean":"Mirrors 2 ","series":"Mirrors","date":2010.0,"imdb":4.9},{"title_clean":"Monster Hunt ","series":"Monster Hunt","date":2015.0,"imdb":6.1},{"title_clean":"Monster Hunt 2 ","series":"Monster Hunt","date":2018.0,"imdb":5.3},{"title_clean":"Monsters, Inc. ","series":"Monsters, Inc.","date":2001.0,"imdb":8.0},{"title_clean":"Monsters University ","series":"Monsters, Inc.","date":2013.0,"imdb":7.3},{"title_clean":"Moon ","series":"Moon","date":2009.0,"imdb":7.9},{"title_clean":"Mute ","series":"Moon","date":2018.0,"imdb":5.4},{"title_clean":"Mortal Kombat ","series":"Mortal Kombat **","date":1995.0,"imdb":5.8},{"title_clean":"Mortal Kombat: Annihilation ","series":"Mortal Kombat **","date":1997.0,"imdb":3.7},{"title_clean":"Bean ","series":"Mr. Bean **","date":1997.0,"imdb":6.5},{"title_clean":"Mr. Bean's Holiday ","series":"Mr. Bean **","date":2007.0,"imdb":6.4},{"title_clean":"Mr Bones ","series":"Mr. Bones","date":2001.0,"imdb":4.8},{"title_clean":"Mr Bones 2: Back from the Past ","series":"Mr. Bones","date":2008.0,"imdb":4.6},{"title_clean":"Unleashing Mr. Darcy ","series":"Mr. Darcy","date":2016.0,"imdb":6.2},{"title_clean":"Marrying Mr. Darcy ","series":"Mr. Darcy","date":2018.0,"imdb":6.1},{"title_clean":"MSG: The Messenger ","series":"MSG: The Messenger","date":2015.0,"imdb":6.7},{"title_clean":"MSG-2 The Messenger ","series":"MSG: The Messenger","date":2015.0,"imdb":7.3},{"title_clean":"Mulan ","series":"Mulan","date":1998.0,"imdb":7.6},{"title_clean":"Mulan II ","series":"Mulan","date":2004.0,"imdb":5.7},{"title_clean":"My Big Fat Greek Wedding ","series":"My Big Fat Greek Wedding","date":2002.0,"imdb":6.5},{"title_clean":"My Big Fat Greek Wedding 2 ","series":"My Big Fat Greek Wedding","date":2016.0,"imdb":6.0},{"title_clean":"My Boss, My Hero ","series":"My Boss...","date":2001.0,"imdb":6.2},{"title_clean":"My Boss, My Teacher ","series":"My Boss...","date":2006.0,"imdb":5.7},{"title_clean":"My Girl ","series":"My Girl","date":1991.0,"imdb":6.9},{"title_clean":"My Girl 2 ","series":"My Girl","date":1994.0,"imdb":5.3},{"title_clean":"My Little Pony: Equestria Girls ","series":"My Little Pony: Friendship is Magic","date":2013.0,"imdb":6.2},{"title_clean":"My Little Pony: Equestria Girls \u2013 Rainbow Rocks ","series":"My Little Pony: Friendship is Magic","date":2014.0,"imdb":6.9},{"title_clean":"My Sassy Girl ","series":"My Sassy Girl","date":2001.0,"imdb":8.0},{"title_clean":"My New Sassy Girl ","series":"My Sassy Girl","date":2016.0,"imdb":4.6},{"title_clean":"Naadodigal ","series":"Naadodigal","date":2009.0,"imdb":7.6},{"title_clean":"Naadodigal 2 ","series":"Naadodigal","date":2020.0,"imdb":5.0},{"title_clean":"Namastey London ","series":"Namaste","date":2007.0,"imdb":7.1},{"title_clean":"Namaste England ","series":"Namaste","date":2018.0,"imdb":1.8},{"title_clean":"Nana ","series":"Nana","date":2005.0,"imdb":7.1},{"title_clean":"Nana 2 ","series":"Nana","date":2006.0,"imdb":6.2},{"title_clean":"Natalee Holloway ","series":"Natalee Holloway","date":2009.0,"imdb":5.5},{"title_clean":"Justice for Natalee Holloway ","series":"Natalee Holloway","date":2011.0,"imdb":5.3},{"title_clean":"National Treasure ","series":"National Treasure","date":2004.0,"imdb":6.9},{"title_clean":"National Treasure: Book of Secrets ","series":"National Treasure","date":2007.0,"imdb":6.5},{"title_clean":"Neighbors ","series":"Neighbors","date":2014.0,"imdb":6.3},{"title_clean":"Neighbors 2: Sorority Rising ","series":"Neighbors","date":2016.0,"imdb":5.7},{"title_clean":"Nim's Island ","series":"Nim's Island","date":2008.0,"imdb":6.0},{"title_clean":"Return to Nim's Island ","series":"Nim's Island","date":2013.0,"imdb":5.0},{"title_clean":"Northpole ","series":"Northpole","date":2014.0,"imdb":6.4},{"title_clean":"Northpole: Open for Christmas ","series":"Northpole","date":2015.0,"imdb":6.2},{"title_clean":"Now You See Me ","series":"Now You See Me","date":2013.0,"imdb":7.3},{"title_clean":"Now You See Me 2 ","series":"Now You See Me","date":2016.0,"imdb":6.5},{"title_clean":"The Nut Job ","series":"The Nut Job","date":2014.0,"imdb":5.7},{"title_clean":"The Nut Job 2: Nutty by Nature ","series":"The Nut Job","date":2017.0,"imdb":5.4},{"title_clean":"The Nutty Professor ","series":"The Nutty Professor (1996 series)","date":1996.0,"imdb":5.6},{"title_clean":"Nutty Professor II: The Klumps ","series":"The Nutty Professor (1996 series)","date":2000.0,"imdb":4.4},{"title_clean":"Oblivion ","series":"Oblivion","date":1994.0,"imdb":5.1},{"title_clean":"Oblivion 2: Backlash ","series":"Oblivion","date":1996.0,"imdb":5.5},{"title_clean":"Octopus ","series":"Octopus","date":2000.0,"imdb":3.1},{"title_clean":"Octopus 2: River of Fear ","series":"Octopus","date":2001.0,"imdb":2.9},{"title_clean":"Summer of Dreams ","series":"Of Dreams","date":2016.0,"imdb":6.1},{"title_clean":"Wedding of Dreams  ","series":"Of Dreams","date":2018.0,"imdb":5.3},{"title_clean":"An Old Fashioned Thanksgiving ","series":"Old Fashioned","date":2008.0,"imdb":6.6},{"title_clean":"An Old Fashioned Christmas ","series":"Old Fashioned","date":2010.0,"imdb":6.0},{"title_clean":"The Omega Code ","series":"The Omega Code","date":1999.0,"imdb":3.6},{"title_clean":"Megiddo: The Omega Code 2 ","series":"The Omega Code","date":2001.0,"imdb":4.0},{"title_clean":"Once Upon a Christmas ","series":"Once Upon a Christmas","date":2000.0,"imdb":5.7},{"title_clean":"Twice Upon a Christmas ","series":"Once Upon a Christmas","date":2001.0,"imdb":5.5},{"title_clean":"Once Were Warriors ","series":"Once Were Warriors","date":1994.0,"imdb":7.9},{"title_clean":"What Becomes of the Broken Hearted? ","series":"Once Were Warriors","date":1999.0,"imdb":6.4},{"title_clean":"One Winter Weekend ","series":"One Winter","date":2018.0,"imdb":6.8},{"title_clean":"One Winter Proposal ","series":"One Winter","date":2019.0,"imdb":6.7},{"title_clean":"OSS 117: Cairo, Nest of Spies ","series":"OSS 117 (2006 series)","date":2006.0,"imdb":7.1},{"title_clean":"OSS 117 \u2013 Lost in Rio ","series":"OSS 117 (2006 series)","date":2009.0,"imdb":6.9},{"title_clean":"The Other Side of Heaven ","series":"The Other Side of Heaven","date":2001.0,"imdb":6.4},{"title_clean":"The Other Side of Heaven 2: Fire of Faith ","series":"The Other Side of Heaven","date":2019.0,"imdb":5.4},{"title_clean":"Ouija ","series":"Ouija","date":2014.0,"imdb":4.5},{"title_clean":"Ouija: Origin of Evil ","series":"Ouija","date":2016.0,"imdb":6.1},{"title_clean":"Pacific Rim ","series":"Pacific Rim","date":2013.0,"imdb":6.9},{"title_clean":"Pacific Rim Uprising ","series":"Pacific Rim","date":2018.0,"imdb":5.6},{"title_clean":"Paddington ","series":"Paddington","date":2014.0,"imdb":7.2},{"title_clean":"Paddington 2 ","series":"Paddington","date":2017.0,"imdb":7.8},{"title_clean":"Paradise Lost: The Child Murders at Robin Hood Hills ","series":"Paradise Lost","date":1996.0,"imdb":8.3},{"title_clean":"Paradise Lost 2: Revelations ","series":"Paradise Lost","date":2000.0,"imdb":7.6},{"title_clean":"Passed Away ","series":"Passed Away","date":1992.0,"imdb":5.9},{"title_clean":"Music from Another Room ","series":"Passed Away","date":1998.0,"imdb":6.4},{"title_clean":"Percy Jackson & the Olympians: The Lightning Thief ","series":"Percy Jackson","date":2010.0,"imdb":5.9},{"title_clean":"Percy Jackson: Sea of Monsters ","series":"Percy Jackson","date":2013.0,"imdb":5.8},{"title_clean":"The Perfect Bride ","series":"The Perfect Bride","date":2017.0,"imdb":6.6},{"title_clean":"The Perfect Bride: Wedding Bells ","series":"The Perfect Bride","date":2018.0,"imdb":6.6},{"title_clean":"The Perfect Son-in-Law? ","series":"The Perfect Son-in-Law?","date":2008.0,"imdb":5.9},{"title_clean":"The Perfect Son-in-Law? 2 ","series":"The Perfect Son-in-Law?","date":2010.0,"imdb":6.5},{"title_clean":"Phoonk ","series":"Phoonk","date":2008.0,"imdb":3.9},{"title_clean":"Phoonk 2 ","series":"Phoonk","date":2010.0,"imdb":3.2},{"title_clean":"The Pink Panther ","series":"The Pink Panther (2006 series)","date":2006.0,"imdb":5.7},{"title_clean":"The Pink Panther 2 ","series":"The Pink Panther (2006 series)","date":2009.0,"imdb":5.6},{"title_clean":"The Adventures of Pinocchio ","series":"Pinocchio (1996 series)","date":1996.0,"imdb":5.2},{"title_clean":"The New Adventures of Pinocchio ","series":"Pinocchio (1996 series)","date":1999.0,"imdb":5.3},{"title_clean":"Piranha 3D ","series":"Piranha (2010 series)","date":2010.0,"imdb":5.4},{"title_clean":"Piranha 3DD ","series":"Piranha (2010 series)","date":2012.0,"imdb":3.7},{"title_clean":"Pirates ","series":"Pirates","date":2005.0,"imdb":7.3},{"title_clean":"Pirates II: Stagnetti's Revenge ","series":"Pirates","date":2008.0,"imdb":7.7},{"title_clean":"Pizza ","series":"Pizza","date":2012.0,"imdb":8.0},{"title_clean":"Pizza II: Villa ","series":"Pizza","date":2013.0,"imdb":6.5},{"title_clean":"Planet of the Sharks ","series":"Planet of the Sharks","date":2016.0,"imdb":2.6},{"title_clean":"Empire of the Sharks ","series":"Planet of the Sharks","date":2017.0,"imdb":2.8},{"title_clean":"Posse ","series":"Posse","date":1993.0,"imdb":5.5},{"title_clean":"Los Locos ","series":"Posse","date":1997.0,"imdb":4.7},{"title_clean":"Poveri ma ricchi ","series":"Poveri ma ricchi","date":2016.0,"imdb":6.1},{"title_clean":"Poveri ma ricchissimi ","series":"Poveri ma ricchi","date":2017.0,"imdb":5.2},{"title_clean":"The Powerpuff Girls Movie ","series":"The Powerpuff Girls **","date":2002.0,"imdb":6.6},{"title_clean":"The Powerpuff Girls: 'Twas the Fight Before Christmas ","series":"The Powerpuff Girls **","date":2003.0,"imdb":7.2},{"title_clean":"Mighty Morphin Power Rangers: The Movie ","series":"Power Rangers ***(theatrical films)","date":1995.0,"imdb":5.2},{"title_clean":"Turbo: A Power Rangers Movie ","series":"Power Rangers ***(theatrical films)","date":1997.0,"imdb":3.7},{"title_clean":"Pretham ","series":"Pretham","date":2016.0,"imdb":6.5},{"title_clean":"Pretham 2 ","series":"Pretham","date":2018.0,"imdb":6.5},{"title_clean":"The Prince of Egypt ","series":"The Prince of Egypt (A)","date":1998.0,"imdb":7.1},{"title_clean":"Joseph: King of Dreams ","series":"The Prince of Egypt (A)","date":2000.0,"imdb":6.5},{"title_clean":"The Princess Diaries ","series":"The Princess Diaries","date":2001.0,"imdb":6.3},{"title_clean":"The Princess Diaries 2: Royal Engagement ","series":"The Princess Diaries","date":2004.0,"imdb":5.8},{"title_clean":"Prison Planet 2: The Armageddon ","series":"Prison Planet","date":1994.0,"imdb":5.2},{"title_clean":"Prison Planet 3: The Revenge ","series":"Prison Planet","date":1998.0,"imdb":6.8},{"title_clean":"Pyaar Ka Punchnama ","series":"Pyaar Ka Punchnama","date":2011.0,"imdb":7.7},{"title_clean":"Pyaar Ka Punchnama 2 ","series":"Pyaar Ka Punchnama","date":2015.0,"imdb":7.3},{"title_clean":"Quarantine ","series":"Quarantine","date":2008.0,"imdb":5.9},{"title_clean":"Quarantine 2: Terminal ","series":"Quarantine","date":2011.0,"imdb":5.2},{"title_clean":"Queen's Messenger ","series":"Queen's Messenger","date":2001.0,"imdb":3.5},{"title_clean":"Witness to a Kill ","series":"Queen's Messenger","date":2001.0,"imdb":4.4},{"title_clean":"Rabbit Without Ears ","series":"Rabbit Without Ears","date":2007.0,"imdb":6.5},{"title_clean":"Rabbit Without Ears 2 ","series":"Rabbit Without Ears","date":2009.0,"imdb":5.6},{"title_clean":"Rage and Honor ","series":"Rage and Honor","date":1992.0,"imdb":5.2},{"title_clean":"Rage and Honor II ","series":"Rage and Honor","date":1993.0,"imdb":5.3},{"title_clean":"The Raid ","series":"The Raid","date":2011.0,"imdb":7.6},{"title_clean":"The Raid 2 ","series":"The Raid","date":2014.0,"imdb":8.0},{"title_clean":"Raju Gari Gadhi ","series":"Raju Gari Gadhi","date":2015.0,"imdb":4.9},{"title_clean":"Raju Gari Gadhi 2 ","series":"Raju Gari Gadhi","date":2017.0,"imdb":5.4},{"title_clean":"Raptor Island ","series":"Raptor Island","date":2004.0,"imdb":2.5},{"title_clean":"Planet Raptor ","series":"Raptor Island","date":2007.0,"imdb":2.7},{"title_clean":"Jackie Brown ","series":"Ray Nicolette","date":1997.0,"imdb":7.5},{"title_clean":"Out of Sight ","series":"Ray Nicolette","date":1998.0,"imdb":7.0},{"title_clean":"ReBoot: Daemon Rising ","series":"ReBoot *","date":2001.0,"imdb":8.6},{"title_clean":"ReBoot: My Two Bobs ","series":"ReBoot *","date":2001.0,"imdb":8.4},{"title_clean":"Red ","series":"Red","date":2010.0,"imdb":7.0},{"title_clean":"Red 2 ","series":"Red","date":2013.0,"imdb":6.6},{"title_clean":"Red Lips ","series":"Red Lips","date":1995.0,"imdb":5.6},{"title_clean":"Red Lips II ","series":"Red Lips","date":1996.0,"imdb":3.8},{"title_clean":"Reeker ","series":"Reeker","date":2005.0,"imdb":5.2},{"title_clean":"No Man's Land: The Rise of Reeker ","series":"Reeker","date":2008.0,"imdb":4.8},{"title_clean":"Rest Stop ","series":"Rest Stop","date":2006.0,"imdb":4.6},{"title_clean":"Rest Stop: Don't Look Back ","series":"Rest Stop","date":2008.0,"imdb":4.7},{"title_clean":"Ride Along ","series":"Ride Along","date":2014.0,"imdb":6.2},{"title_clean":"Ride Along 2 ","series":"Ride Along","date":2016.0,"imdb":5.9},{"title_clean":"Rio ","series":"Rio","date":2011.0,"imdb":6.9},{"title_clean":"Rio 2 ","series":"Rio","date":2014.0,"imdb":6.3},{"title_clean":"Road Trip ","series":"Road Trip","date":2000.0,"imdb":6.4},{"title_clean":"Road Trip: Beer Pong ","series":"Road Trip","date":2009.0,"imdb":4.9},{"title_clean":"Robo-Dog ","series":"Robo-Dog","date":2015.0,"imdb":4.4},{"title_clean":"Robo-Dog: Airborne ","series":"Robo-Dog","date":2017.0,"imdb":4.8},{"title_clean":"Rolie Polie Olie: The Great Defender of Fun ","series":"Rolie Polie Olie (A) *","date":2002.0,"imdb":6.0},{"title_clean":"Rolie Polie Olie: The Baby Bot Chase ","series":"Rolie Polie Olie (A) *","date":2003.0,"imdb":6.4},{"title_clean":"Romy and Michele's High School Reunion ","series":"Romy and Michele","date":1997.0,"imdb":6.2},{"title_clean":"Romy and Michele: In the Beginning ","series":"Romy and Michele","date":2005.0,"imdb":4.1},{"title_clean":"Rose Red ","series":"Stephen King's Rose Red","date":2002.0,"imdb":6.8},{"title_clean":"The Diary of Ellen Rimbauer ","series":"Stephen King's Rose Red","date":2003.0,"imdb":5.5},{"title_clean":"The Mystery of the Yellow Room ","series":"Rouletabille (2003 series)","date":2003.0,"imdb":6.3},{"title_clean":"Le Parfum de la dame en noir ","series":"Rouletabille (2003 series)","date":2005.0,"imdb":5.7},{"title_clean":"Royal Tramp ","series":"Royal Tramp","date":1992.0,"imdb":7.2},{"title_clean":"Royal Tramp II ","series":"Royal Tramp","date":1992.0,"imdb":7.0},{"title_clean":"Running Out of Time ","series":"Running Out of Time","date":1999.0,"imdb":7.4},{"title_clean":"Running Out of Time 2 ","series":"Running Out of Time","date":2001.0,"imdb":5.8},{"title_clean":"Saayad ","series":"Saayad","date":2012.0,"imdb":6.2},{"title_clean":"Saayad 2 ","series":"Saayad","date":2017.0,"imdb":8.3},{"title_clean":"Senario: The Movie ","series":"Saiful Azam Senario","date":1999.0,"imdb":7.2},{"title_clean":"Senario the Movie Episode 2: Beach Boys ","series":"Saiful Azam Senario","date":2009.0,"imdb":7.0},{"title_clean":"Naan ","series":"Salim","date":2012.0,"imdb":7.5},{"title_clean":"Salim ","series":"Salim","date":2014.0,"imdb":6.8},{"title_clean":"Santa Baby ","series":"Santa Baby","date":2006.0,"imdb":5.6},{"title_clean":"Santa Baby 2: Christmas Maybe ","series":"Santa Baby","date":2009.0,"imdb":5.5},{"title_clean":"Forgetting Sarah Marshall ","series":"Sarah Marshall\/Aldous Snow","date":2008.0,"imdb":7.1},{"title_clean":"Get Him to the Greek ","series":"Sarah Marshall\/Aldous Snow","date":2010.0,"imdb":6.4},{"title_clean":"Saved by the Bell: Hawaiian Style ","series":"Saved by the Bell ****","date":1992.0,"imdb":6.1},{"title_clean":"Saved by the Bell: Wedding in Las Vegas ","series":"Saved by the Bell ****","date":1994.0,"imdb":6.4},{"title_clean":"Save the Last Dance ","series":"Save the Last Dance","date":2001.0,"imdb":6.2},{"title_clean":"Save the Last Dance 2 ","series":"Save the Last Dance","date":2006.0,"imdb":5.3},{"title_clean":"Saviour of the Soul ","series":"Saviour of the Soul","date":1991.0,"imdb":6.2},{"title_clean":"Saviour of the Soul II ","series":"Saviour of the Soul","date":1992.0,"imdb":5.0},{"title_clean":"Score ","series":"Score","date":1995.0,"imdb":6.4},{"title_clean":"Score 2: The Big Fight ","series":"Score","date":1999.0,"imdb":5.6},{"title_clean":"Screamers ","series":"Screamers","date":1995.0,"imdb":6.4},{"title_clean":"Screamers: The Hunting ","series":"Screamers","date":2009.0,"imdb":4.7},{"title_clean":"The Secret Life of Pets ","series":"The Secret Life of Pets","date":2016.0,"imdb":6.5},{"title_clean":"The Secret Life of Pets 2 ","series":"The Secret Life of Pets","date":2019.0,"imdb":6.5},{"title_clean":"See No Evil ","series":"See No Evil","date":2006.0,"imdb":5.1},{"title_clean":"See No Evil 2 ","series":"See No Evil","date":2014.0,"imdb":4.7},{"title_clean":"Sex and the City ","series":"Sex and the City *","date":2008.0,"imdb":5.6},{"title_clean":"Sex and the City 2 ","series":"Sex and the City *","date":2010.0,"imdb":4.5},{"title_clean":"Sex Is Zero ","series":"Sex Is Zero","date":2002.0,"imdb":6.6},{"title_clean":"Sex Is Zero 2 ","series":"Sex Is Zero","date":2007.0,"imdb":6.1},{"title_clean":"Sharkwater ","series":"Sharkwater","date":2006.0,"imdb":8.0},{"title_clean":"Sharkwater Extinction ","series":"Sharkwater","date":2018.0,"imdb":7.7},{"title_clean":"The Hound of the Baskervilles ","series":"Sherlock Holmes (2002 series with Ian Hart as Dr. Watson)","date":2002.0,"imdb":6.6},{"title_clean":"Sherlock Holmes and the Case of the Silk Stocking ","series":"Sherlock Holmes (2002 series with Ian Hart as Dr. Watson)","date":2004.0,"imdb":6.8},{"title_clean":"Sherlock Holmes ","series":"Sherlock Holmes (2009 series)","date":2009.0,"imdb":7.6},{"title_clean":"Sherlock Holmes: A Game of Shadows ","series":"Sherlock Holmes (2009 series)","date":2011.0,"imdb":7.5},{"title_clean":"Shootout at Lokhandwala ","series":"Shootout","date":2007.0,"imdb":7.1},{"title_clean":"Shootout at Wadala ","series":"Shootout","date":2013.0,"imdb":5.9},{"title_clean":"Shred ","series":"Shred","date":2008.0,"imdb":3.9},{"title_clean":"Revenge of the Boarding School Dropouts ","series":"Shred","date":2009.0,"imdb":3.0},{"title_clean":"Pyaar Ke Side Effects ","series":"Side\/Effects","date":2006.0,"imdb":6.7},{"title_clean":"Shaadi Ke Side Effects ","series":"Side\/Effects","date":2014.0,"imdb":5.6},{"title_clean":"Silent Hill ","series":"Silent Hill","date":2006.0,"imdb":6.5},{"title_clean":"Silent Hill: Revelation ","series":"Silent Hill","date":2012.0,"imdb":5.0},{"title_clean":"Silent M\u00f6bius ","series":"Silent M\u00f6bius","date":1991.0,"imdb":6.6},{"title_clean":"Silent M\u00f6bius 2 ","series":"Silent M\u00f6bius","date":1992.0,"imdb":6.5},{"title_clean":"Sin City ","series":"Sin City","date":2005.0,"imdb":8.0},{"title_clean":"Sin City: A Dame to Kill For ","series":"Sin City","date":2014.0,"imdb":6.5},{"title_clean":"Single White Female ","series":"Single White Female","date":1992.0,"imdb":6.4},{"title_clean":"Single White Female 2: The Psycho ","series":"Single White Female","date":2005.0,"imdb":4.1},{"title_clean":"Sister Act ","series":"Sister Act","date":1992.0,"imdb":6.4},{"title_clean":"Sister Act 2: Back in the Habit ","series":"Sister Act","date":1993.0,"imdb":5.6},{"title_clean":"The Sisterhood of the Traveling Pants ","series":"The Sisterhood of the Traveling Pants","date":2005.0,"imdb":6.5},{"title_clean":"The Sisterhood of the Traveling Pants 2 ","series":"The Sisterhood of the Traveling Pants","date":2008.0,"imdb":6.2},{"title_clean":"The Ski Trip ","series":"The Ski Trip","date":2004.0,"imdb":5.0},{"title_clean":"Friends & Lovers: The Ski Trip 2 ","series":"The Ski Trip","date":2008.0,"imdb":6.5},{"title_clean":"Skyline ","series":"Skyline","date":2010.0,"imdb":4.4},{"title_clean":"Beyond Skyline ","series":"Skyline","date":2017.0,"imdb":5.3},{"title_clean":"Smoke ","series":"Smoke\/Blue in the Face","date":1995.0,"imdb":7.4},{"title_clean":"Blue in the Face ","series":"Smoke\/Blue in the Face","date":1995.0,"imdb":6.7},{"title_clean":"Smokin' Aces ","series":"Smokin' Aces","date":2006.0,"imdb":6.7},{"title_clean":"Smokin' Aces 2: Assassins' Ball ","series":"Smokin' Aces","date":2010.0,"imdb":5.1},{"title_clean":"The Smurfs ","series":"The Smurfs *","date":2011.0,"imdb":5.4},{"title_clean":"The Smurfs 2 ","series":"The Smurfs *","date":2013.0,"imdb":5.3},{"title_clean":"Snow ","series":"Snow","date":2004.0,"imdb":6.6},{"title_clean":"Snow 2: Brain Freeze ","series":"Snow","date":2008.0,"imdb":6.2},{"title_clean":"S\u00f6karna ","series":"S\u00f6karna","date":1993.0,"imdb":4.6},{"title_clean":"S\u00f6karna: \u00c5terkomsten ","series":"S\u00f6karna","date":2006.0,"imdb":2.5},{"title_clean":"Somebody Help Me ","series":"Somebody Help Me","date":2007.0,"imdb":4.2},{"title_clean":"Somebody Help Me 2 ","series":"Somebody Help Me","date":2010.0,"imdb":4.0},{"title_clean":"Space Chimps ","series":"Space Chimps","date":2008.0,"imdb":4.5},{"title_clean":"Space Chimps 2: Zartog Strikes Back ","series":"Space Chimps","date":2010.0,"imdb":2.7},{"title_clean":"Speed ","series":"Speed","date":1994.0,"imdb":7.2},{"title_clean":"Speed 2: Cruise Control ","series":"Speed","date":1997.0,"imdb":3.9},{"title_clean":"The SpongeBob SquarePants Movie ","series":"SpongeBob SquarePants *","date":2004.0,"imdb":7.1},{"title_clean":"The SpongeBob Movie: Sponge Out of Water ","series":"SpongeBob SquarePants *","date":2015.0,"imdb":6.0},{"title_clean":"Stir of Echoes ","series":"Stir of Echoes","date":1999.0,"imdb":7.0},{"title_clean":"Stir of Echoes: The Homecoming ","series":"Stir of Echoes","date":2007.0,"imdb":4.6},{"title_clean":"Z Storm ","series":"Storm","date":2014.0,"imdb":5.3},{"title_clean":"S Storm ","series":"Storm","date":2016.0,"imdb":5.1},{"title_clean":"The Strangers ","series":"The Strangers","date":2008.0,"imdb":6.2},{"title_clean":"The Strangers: Prey at Night ","series":"The Strangers","date":2018.0,"imdb":5.2},{"title_clean":"Street Kings ","series":"Street Kings","date":2008.0,"imdb":6.8},{"title_clean":"Street Kings 2: Motor City ","series":"Street Kings","date":2011.0,"imdb":4.9},{"title_clean":"StreetDance 3D ","series":"Street Dance","date":2010.0,"imdb":5.9},{"title_clean":"StreetDance 2 ","series":"Street Dance","date":2012.0,"imdb":5.7},{"title_clean":"Stripteaser ","series":"Stripteaser","date":1995.0,"imdb":4.7},{"title_clean":"Stripteaser II ","series":"Stripteaser","date":1997.0,"imdb":4.7},{"title_clean":"Student of the Year ","series":"Student of the Year","date":2012.0,"imdb":5.4},{"title_clean":"Student of the Year 2 ","series":"Student of the Year","date":2019.0,"imdb":2.3},{"title_clean":"Style ","series":"Style","date":2001.0,"imdb":6.7},{"title_clean":"Xcuse Me ","series":"Style","date":2003.0,"imdb":5.7},{"title_clean":"Superman: The Last Son of Krypton ","series":"Superman (DC Animated Universe) **","date":1996.0,"imdb":7.7},{"title_clean":"The Batman Superman Movie: World's Finest ","series":"Superman (DC Animated Universe) **","date":1997.0,"imdb":7.8},{"title_clean":"Superman\/Batman: Public Enemies ","series":"Superman\/Batman (DC Universe Animated Original Movies)","date":2009.0,"imdb":7.2},{"title_clean":"Superman\/Batman: Apocalypse ","series":"Superman\/Batman (DC Universe Animated Original Movies)","date":2010.0,"imdb":7.1},{"title_clean":"Super Size Me ","series":"Super Size Me","date":2004.0,"imdb":7.2},{"title_clean":"Super Size Me 2: Holy Chicken! ","series":"Super Size Me","date":2017.0,"imdb":7.1},{"title_clean":"Super Troopers ","series":"Super Troopers","date":2001.0,"imdb":7.1},{"title_clean":"Super Troopers 2 ","series":"Super Troopers","date":2018.0,"imdb":6.0},{"title_clean":"Surf's Up ","series":"Surf's Up (A)","date":2007.0,"imdb":6.7},{"title_clean":"Surf's Up 2: WaveMania ","series":"Surf's Up (A)","date":2017.0,"imdb":4.6},{"title_clean":"Tanu Weds Manu ","series":"Tanu Weds Manu","date":2011.0,"imdb":6.8},{"title_clean":"Tanu Weds Manu: Returns ","series":"Tanu Weds Manu","date":2015.0,"imdb":7.6},{"title_clean":"Ted ","series":"Ted","date":2012.0,"imdb":6.9},{"title_clean":"Ted 2 ","series":"Ted","date":2015.0,"imdb":6.3},{"title_clean":"Teen Beach Movie ","series":"Teen Beach","date":2013.0,"imdb":5.9},{"title_clean":"Teen Beach 2 ","series":"Teen Beach","date":2015.0,"imdb":6.1},{"title_clean":"Teenage Mutant Ninja Turtles ","series":"Teenage Mutant Ninja Turtles (2014 series)","date":2014.0,"imdb":5.8},{"title_clean":"Teenage Mutant Ninja Turtles: Out of the Shadows ","series":"Teenage Mutant Ninja Turtles (2014 series)","date":2016.0,"imdb":6.0},{"title_clean":"Tere Bin Laden ","series":"Tere Bin Laden","date":2010.0,"imdb":7.2},{"title_clean":"Tere Bin Laden: Dead or Alive ","series":"Tere Bin Laden","date":2016.0,"imdb":4.3},{"title_clean":"The Texas Chainsaw Massacre ","series":"The Texas Chainsaw Massacre (2003 series)","date":2003.0,"imdb":6.2},{"title_clean":"The Texas Chainsaw Massacre: The Beginning ","series":"The Texas Chainsaw Massacre (2003 series)","date":2006.0,"imdb":5.8},{"title_clean":"Three ","series":"Three","date":2002.0,"imdb":7.0},{"title_clean":"Three... Extremes ","series":"Three","date":2004.0,"imdb":7.0},{"title_clean":"Ek Tha Tiger ","series":"Tiger","date":2012.0,"imdb":5.5},{"title_clean":"Tiger Zinda Hai ","series":"Tiger","date":2017.0,"imdb":6.0},{"title_clean":"Time for Me to Come Home for Christmas ","series":"Time to Come Home for Christmas","date":2018.0,"imdb":6.8},{"title_clean":"Time for You to Come Home for Christmas ","series":"Time to Come Home for Christmas","date":2019.0,"imdb":7.0},{"title_clean":"Lara Croft: Tomb Raider ","series":"Tomb Raider","date":2001.0,"imdb":5.8},{"title_clean":"Lara Croft Tomb Raider: The Cradle of Life ","series":"Tomb Raider","date":2003.0,"imdb":5.5},{"title_clean":"Tooth Fairy ","series":"Tooth Fairy","date":2010.0,"imdb":5.0},{"title_clean":"Tooth Fairy 2 ","series":"Tooth Fairy","date":2012.0,"imdb":3.7},{"title_clean":"Trainspotting ","series":"Trainspotting","date":1996.0,"imdb":8.1},{"title_clean":"T2 Trainspotting ","series":"Trainspotting","date":2017.0,"imdb":7.2},{"title_clean":"Transmorphers ","series":"Transmorphers","date":2007.0,"imdb":1.7},{"title_clean":"Transmorphers: Fall of Man ","series":"Transmorphers","date":2009.0,"imdb":2.0},{"title_clean":"What Happened to Pete ","series":"Trees Lounge","date":1992.0,"imdb":6.7},{"title_clean":"Trees Lounge ","series":"Trees Lounge","date":1996.0,"imdb":7.1},{"title_clean":"Trekkies ","series":"Trekkies","date":1997.0,"imdb":6.9},{"title_clean":"Trekkies 2 ","series":"Trekkies","date":2004.0,"imdb":6.4},{"title_clean":"Trick: The Movie ","series":"Trick","date":2002.0,"imdb":6.4},{"title_clean":"Trick: The Movie 2 ","series":"Trick","date":2006.0,"imdb":6.1},{"title_clean":"Marius ","series":"La Trilogie Marseillaise","date":2013.0,"imdb":6.7},{"title_clean":"Fanny ","series":"La Trilogie Marseillaise","date":2013.0,"imdb":6.8},{"title_clean":"Trolls ","series":"Trolls *","date":2016.0,"imdb":6.5},{"title_clean":"Trolls World Tour ","series":"Trolls *","date":2020.0,"imdb":6.1},{"title_clean":"Think Like a Man ","series":"Think Like a Man","date":2012.0,"imdb":6.6},{"title_clean":"Think Like a Man Too ","series":"Think Like a Man","date":2014.0,"imdb":5.8},{"title_clean":"Tum Bin ","series":"Tum Bin","date":2001.0,"imdb":7.5},{"title_clean":"Tum Bin 2 ","series":"Tum Bin","date":2016.0,"imdb":4.8},{"title_clean":"Twin Peaks: Fire Walk with Me ","series":"Twin Peaks Prequels *","date":1992.0,"imdb":7.3},{"title_clean":"Twin Peaks: The Missing Pieces ","series":"Twin Peaks Prequels *","date":2014.0,"imdb":7.8},{"title_clean":"Twitches ","series":"Twitches","date":2005.0,"imdb":5.7},{"title_clean":"Twitches Too ","series":"Twitches","date":2007.0,"imdb":5.8},{"title_clean":"Two Can Play That Game ","series":"Two\/Three Can Play That Game","date":2001.0,"imdb":6.2},{"title_clean":"Three Can Play That Game ","series":"Two\/Three Can Play That Game","date":2007.0,"imdb":4.7},{"title_clean":"Unbroken ","series":"Unbroken","date":2014.0,"imdb":7.2},{"title_clean":"Unbroken: Path to Redemption ","series":"Unbroken","date":2018.0,"imdb":5.8},{"title_clean":"Under Siege ","series":"Under Siege","date":1992.0,"imdb":6.5},{"title_clean":"Under Siege 2: Dark Territory ","series":"Under Siege","date":1995.0,"imdb":5.5},{"title_clean":"Undercover Brother ","series":"Undercover Brother","date":2002.0,"imdb":5.8},{"title_clean":"Undercover Brother 2 ","series":"Undercover Brother","date":2019.0,"imdb":3.4},{"title_clean":"Unfriended ","series":"Unfriended","date":2014.0,"imdb":5.5},{"title_clean":"Unfriended: Dark Web ","series":"Unfriended","date":2018.0,"imdb":5.9},{"title_clean":"The Untold Story ","series":"The Untold Story","date":1997.0,"imdb":7.0},{"title_clean":"The Untold Story 2 ","series":"The Untold Story","date":1998.0,"imdb":5.5},{"title_clean":"Upendra ","series":"Upendra","date":1999.0,"imdb":8.8},{"title_clean":"Uppi 2 ","series":"Upendra","date":2015.0,"imdb":8.0},{"title_clean":"Uppukandam Brothers ","series":"Uppukandam Brothers","date":1993.0,"imdb":6.4},{"title_clean":"Uppukandam Brothers: Back in Action ","series":"Uppukandam Brothers","date":2011.0,"imdb":2.8},{"title_clean":"Vaastav: The Reality ","series":"Vaastav: The Reality","date":1999.0,"imdb":8.0},{"title_clean":"Hathyar ","series":"Vaastav: The Reality","date":2002.0,"imdb":5.8},{"title_clean":"Vacancy ","series":"Vacancy","date":2007.0,"imdb":6.2},{"title_clean":"Vacancy 2: The First Cut ","series":"Vacancy","date":2008.0,"imdb":5.0},{"title_clean":"Interview with the Vampire ","series":"The Vampire Chronicles","date":1994.0,"imdb":7.6},{"title_clean":"Queen of the Damned ","series":"The Vampire Chronicles","date":2002.0,"imdb":5.3},{"title_clean":"Jonah: A VeggieTales Movie ","series":"VeggieTales *","date":2002.0,"imdb":6.4},{"title_clean":"The Pirates Who Don't Do Anything: A VeggieTales Movie ","series":"VeggieTales *","date":2008.0,"imdb":5.6},{"title_clean":"Vennila Kabadi Kuzhu ","series":"Vennila Kabadi Kuzhu","date":2009.0,"imdb":7.3},{"title_clean":"Vennila Kabaddi Kuzhu 2 ","series":"Vennila Kabadi Kuzhu","date":2019.0,"imdb":5.5},{"title_clean":"Victory ","series":"Victory","date":2013.0,"imdb":7.1},{"title_clean":"Victory 2 ","series":"Victory","date":2018.0,"imdb":7.7},{"title_clean":"Virtual Encounters ","series":"Virtual Encounters","date":1996.0,"imdb":4.1},{"title_clean":"Virtual Encounters 2 ","series":"Virtual Encounters","date":1998.0,"imdb":2.9},{"title_clean":"Waiting... ","series":"Waiting...","date":2005.0,"imdb":6.8},{"title_clean":"Still Waiting... ","series":"Waiting...","date":2009.0,"imdb":4.9},{"title_clean":"Walang matigas na pulis sa matinik na misis ","series":"Walang matigas na pulis","date":1994.0,"imdb":5.4},{"title_clean":"Yes Darling: Walang matigas na pulis 2 ","series":"Walang matigas na pulis","date":1997.0,"imdb":4.3},{"title_clean":"The Incredible Adventures of Wallace & Gromit ","series":"Wallace & Gromit **","date":2001.0,"imdb":8.6},{"title_clean":"Wallace & Gromit: The Curse of the Were-Rabbit ","series":"Wallace & Gromit **","date":2005.0,"imdb":7.4},{"title_clean":"H.G. Wells' War of the Worlds ","series":"H.G. Wells' War of the Worlds","date":2005.0,"imdb":5.8},{"title_clean":"War of the Worlds 2: The Next Wave ","series":"H.G. Wells' War of the Worlds","date":2008.0,"imdb":2.0},{"title_clean":"Wayne's World ","series":"Wayne's World","date":1992.0,"imdb":7.0},{"title_clean":"Wayne's World 2 ","series":"Wayne's World","date":1993.0,"imdb":6.2},{"title_clean":"Welcome to the South ","series":"Welcome to the...","date":2010.0,"imdb":6.6},{"title_clean":"Welcome to the North ","series":"Welcome to the...","date":2012.0,"imdb":5.3},{"title_clean":"White Fang ","series":"White Fang","date":1991.0,"imdb":6.7},{"title_clean":"White Fang 2: Myth of the White Wolf ","series":"White Fang","date":1994.0,"imdb":5.4},{"title_clean":"The Whole Nine Yards ","series":"The Whole Nine Yards","date":2000.0,"imdb":6.7},{"title_clean":"The Whole Ten Yards ","series":"The Whole Nine Yards","date":2004.0,"imdb":5.5},{"title_clean":"Why Did I Get Married? ","series":"Why Did I Get Married?","date":2007.0,"imdb":5.9},{"title_clean":"Why Did I Get Married Too? ","series":"Why Did I Get Married?","date":2010.0,"imdb":4.7},{"title_clean":"The Wind in the Willows ","series":"The Wind in the Willows (A)","date":1995.0,"imdb":7.7},{"title_clean":"The Willows in Winter ","series":"The Wind in the Willows (A)","date":1996.0,"imdb":8.0},{"title_clean":"Without a Paddle ","series":"Without a Paddle","date":2004.0,"imdb":5.9},{"title_clean":"Without a Paddle: Nature's Calling ","series":"Without a Paddle","date":2009.0,"imdb":4.0},{"title_clean":"Wreck-It Ralph ","series":"Wreck-It Ralph","date":2012.0,"imdb":7.7},{"title_clean":"Ralph Breaks the Internet ","series":"Wreck-It Ralph","date":2018.0,"imdb":7.1},{"title_clean":"The X-Files ","series":"The X-Files ***","date":1998.0,"imdb":8.0},{"title_clean":"The X-Files: I Want to Believe ","series":"The X-Files ***","date":2008.0,"imdb":5.9},{"title_clean":"Ye Re Ye Re Paisa ","series":"Ye Re Ye Re Paisa","date":2018.0,"imdb":7.4},{"title_clean":"Ye Re Ye Re Paisa 2 ","series":"Ye Re Ye Re Paisa","date":2019.0,"imdb":5.5},{"title_clean":"The Young Fighters ","series":"The Young Fighters","date":1994.0,"imdb":7.5},{"title_clean":"Young Fighters Forever ","series":"The Young Fighters","date":1995.0,"imdb":8.0},{"title_clean":"Zombieland ","series":"Zombieland","date":2009.0,"imdb":7.6},{"title_clean":"Zombieland: Double Tap ","series":"Zombieland","date":2019.0,"imdb":6.7},{"title_clean":"The Mask of Zorro ","series":"Zorro (1998 series)","date":1998.0,"imdb":6.7},{"title_clean":"The Legend of Zorro ","series":"Zorro (1998 series)","date":2005.0,"imdb":6.0}]